Workbook

Sheet Instruções
A1: INSTRUÇÕES DE USO
A2: Fluxo recomendado para aplicação, monitoramento e atualização do instrumento de controle da documentação escolar
A5: 1. Atualizar o cadastro | B5: Revisar os 217 registros de endereço e completar atos legais, vigência, responsáveis, data da atualização e observações cadastrais.
A6: 2. Planejar a verificação | B6: Criar ID único na aba Plano de Auditoria, selecionar a unidade, definir tipo, prioridade, datas e equipe responsável.
A7: 3. Avaliar os 53 registros | B7: Na Auditoria Documental, classificar cada item como Conforme, Parcialmente conforme, Não conforme, Não se aplica ou Não avaliado e indicar a evidência.
A8: 4. Aplicar a pontuação | B8: Conforme = 100% do peso; Parcialmente conforme = 50%; Não conforme/Não avaliado = 0%; Não se aplica = excluído mediante justificativa.
A9: 5. Usar a síntese da visita | B9: Os itens VIS-01 a VIS-12 reproduzem integralmente a última página do Checklist e alimentam automaticamente a aba Checklist da Visita.
A10: 6. Evitar dupla contagem | B10: Os 12 itens de síntese possuem peso zero. O índice global considera os 41 itens técnicos, preservando todos os registros sem duplicar sua influência estatística.
A11: 7. Tratar pendências | B11: Registrar no Plano de Ação cada não conformidade relevante, com prioridade, responsável, prazo, evidência e validação da CDE.
A12: 8. Monitorar resultados | B12: Utilizar Dashboard e Relatórios para reuniões de gestão, priorizando atos legais, vida escolar, arquivos, carga horária e divergências documentais.
A15: CRITÉRIOS DE CLASSIFICAÇÃO
A16: Situação | B16: Pontuação | C16: Significado | D16: Encaminhamento
A17: Conforme | B17: 100% do peso | C17: Evidência integral, válida e coerente. | D17: Manter e monitorar.
A18: Parcialmente conforme | B18: 50% do peso | C18: Atendimento incompleto ou evidência parcial. | D18: Complementar e registrar prazo.
A19: Não conforme | B19: 0% | C19: Ausência, invalidade ou divergência relevante. | D19: Abrir ação corretiva.
A20: Não se aplica | B20: Excluído | C20: Item incompatível com a oferta/situação da unidade. | D20: Justificar formalmente.
A23: FONTES INCORPORADAS AO INSTRUMENTO
A24: Checklist Coordenadoria de Documentação Escolar.pdf | B24: 53 registros incorporados integralmente: 41 itens técnicos e 12 itens do Checklist para a visita.
A25: Endereço de Unidades escolares por Distrito e_Bairro.xlsx | B25: 217 unidades incorporadas com distrito, bairro, vínculo, INEP, situação, tipo, endereço, CEP, telefone e e-mail.

Sheet Cadastro Unidades
A2: Base territorial unificada das unidades municipais e OSCs/conveniadas — organizada por distrito e bairro
A5: Distrito | B5: Bairro | C5: Rede/Vínculo | D5: Código INEP/MEC | E5: Nome da unidade | F5: Situação | G5: Tipo de unidade | H5: Distrito do anexo | I5: Tipo do prédio | J5: Tipo de contrato | K5: Zona | L5: Endereço | M5: Número | N5: Complemento | O5: CEP | P5: Telefone | Q5: E-mail | R5: Ato de criação | S5: Ato de autorização/credenciamento/reconhecimento | T5: Vigência do ato | U5: Diretor(a) | V5: Contato | W5: Matrícula | X5: Secretário(a) escolar | Y5: Matrícula 2 | Z5: Data da atualização | AA5: Observações cadastrais
A6: DABEL | B6: BATISTA CAMPOS | C6: MUNICIPAL | D6: 15548058 | E6: ESCOLA MUNICIPAL PROFESSORA MARIA AUXILIADORA MARTINS GONCALVES | F6: ATIVA | G6: SEDE | H6: DABEL | I6: MUNICIPAL | J6: ALUGUEL | K6: URBANA | L6: RUA SAO MIGUEL | M6: 557 | N6: ENTRE TUPINAMBS E APINAGS ENTRE TUPINAMBAS E APINAGES | O6: 66033112 | Q6: iris.santana@semec.belem.pa.gov.br | R6: DECRETO Nº 96.781/2020 - PMB, DE 21 DE JULHO DE 2020 | S6: NÃO LOCALIZADO NO SITE DO CME BELÉM | U6: IRIS CORREA SANTANA - | V6: 981994474 | W6: 0351229- 019 | X6: SEM SECRETARIO | Z6: 46265
A7: DABEL | B7: GUAMA | C7: MUNICIPAL | D7: 15040801 | E7: ANEXO BARAO DE MAMORE DA EM FRANCISCO DA SILVA NUNES | F7: ATIVA | G7: ANEXO | H7: DABEL | I7: MUNICIPAL | J7: ALUGUEL | K7: URBANA | L7: TRAVESSA QUATORZE DE ABRIL | M7: 2321 | N7: CASA | O7: 66063485 | Q7: upbaraodemamore@semec.belem.pa.gov.br | S7: 10/2025 - CME, DE 17/06/2025 | T7: 47650 | U7: CLAUDICEIA BAIA FERREIRA | V7: 982020921 | W7: 1859030- 014 | X7: SEM SECRETARIO | Z7: 46265
A8: DABEL | B8: JURUNAS | C8: MUNICIPAL | D8: 15040720 | E8: ESCOLA MUNICIPAL PROF MIGUEL PERNAMBUCO FILHO | F8: ATIVA | G8: SEDE | H8: DABEL | I8: MUNICIPAL | J8: PROPRIA | K8: URBANA | L8: AVENIDA ROBERTO CAMELIER | M8: 825 | N8: RUA NOVA E PSG SANTA TEREZA | O8: 66025455 | Q8: emeif.mpfilho@semec.pmb.pa.gov.br | S8: 072/2018 - CME, DE 18/12/2018 | T8: 44906 | U8: LADYANNA CHRISTINA DE LIMA | V8: 982634727 | W8: 0349127- 018 | X8: ELIANE SANTANA HOMEM | Y8: 0390950-017 | Z8: 46265
A9: DABEL | B9: MARCO | C9: MUNICIPAL | D9: 15040860 | E9: ANEXO CASA DA CRIANCA SANTA INES DA EM ALZIRA PERNAMBUCO | F9: ATIVA | G9: ANEXO | H9: DABEL | I9: MUNICIPAL | J9: ALUGUEL | K9: URBANA | L9: AVENIDA JOAO PAULO II | M9: 1725 | N9: CASA ENTRE TV. LOMAS VALENTINAS E TV. ENEAS PINHEIRO | O9: 66095495 | Q9: casadacriancastaines@semec.belem.pa.gov.br | S9: 58/2019 - CME, DE 20/12/2019 | T9: 44989 | U9: ANA DEISE PINTO DA SILVA | Z9: 46265
A10: DABEL | B10: MARCO | C10: OSC/CONVENIADA | D10: 15182754 | E10: CENTRO EDUCACIONAL ARTE DE EDUCAR OSC ANEXO INSTITUTO ACELERA AMAZONIA | F10: ATIVA | G10: ANEXO | J10: SUBVENÇÃO | K10: URBANA | L10: PASSAGEM LINDOLFO COLLOR | M10: 115 | O10: 66095310 | R10: OSC - NÃO NECESSITA ATO DE CRIAÇÃO | S10: NÃO LOCALIZADO NO SITE DO CME BELÉM | Z10: 46265
A11: DABEL | B11: MARCO | C11: MUNICIPAL | D11: 15040860 | E11: ESCOLA MUNICIPAL ALZIRA PERNAMBUCO | F11: ATIVA | G11: SEDE | H11: DABEL | I11: MUNICIPAL | J11: PROPRIA | K11: URBANA | L11: TRAVESSA PEREBEBUI | M11: 1995 | N11: ENTRE AV. DUQUE DE CAXIAS E VISC. DE INHAUMA | O11: 66095661 | S11: 58/2019 - CME, DE 20/12/2019 | T11: 44989 | U11: ROSEANE RODRIGUES SIQUEIRA | W11: 0347000- 010 | X11: ABELARDO BARROSO BRABO | Y11: 1954261-010 | Z11: 46265
A12: DABEL | B12: MARCO | C12: MUNICIPAL | D12: 15181677 | E12: ESCOLA MUNICIPAL LIONS CLUBE DE BELEM | F12: ATIVA | G12: SEDE | H12: DABEL | I12: MUNICIPAL | J12: COMODATO | K12: URBANA | L12: PASSAGEM SAO JOSE | M12: 8 | O12: 66095570 | Q12: cclionsclubedebelem@semec.belem.pa.gov.br | R12: DECRETO Nº 113.717/2025 - PMB, DE 23 DE JUNHO DE 2025 | S12: 22/2025 - CME, DE 09/09/2025 | T12: 46273 | U12: ROSANGELA PANTOJA MOTA | V12: 987325386 | W12: 0421820- 012 | X12: IZABEL SEIXAS DE OLIVEIRA | Y12: 0053821-017 | Z12: 46265
A13: DABEL | B13: MARCO | C13: MUNICIPAL | D13: 15547299 | E13: ESCOLA MUNICIPAL PROFESSORA LUCIA SOARES CASTRO | F13: ATIVA | G13: SEDE | H13: DABEL | I13: MUNICIPAL | J13: PROPRIA | K13: URBANA | L13: AVENIDA JOAO PAULO II | M13: 1538 | N13: ENTRE LOMAS E ANGUSTURA | O13: 66095494 | Q13: emeiluciacastro@gmail.com | R13: DECRETO Nº 96.504/2020 - PMB, DE 16 DE JUNHO DE 2020. | S13: 12/2022 - CME, DE 21/12/2022 | T13: 46741 | U13: LUCELINA DE SOUSA LIMA | V13: 981260269 | W13: 0347663- 010 | Z13: 46265
A14: DABEL | B14: MARCO | C14: MUNICIPAL | D14: 15174557 | E14: ESCOLA MUNICIPAL PROFESSORA RAIMUNDA LUCIA GUERREIRO | F14: ATIVA | G14: SEDE | H14: DABEL | I14: MUNICIPAL | J14: ALUGUEL | K14: URBANA | L14: TRAVESSA LOMAS VALENTINAS | M14: 2892 | N14: ENTRE JOAO PAULO E PASSAGEM PIO X | O14: 66093677 | Q14: profraimundaluciaguerreiro@semec.belem.pa.gov.br | R14: DECRETO Nº 96.325/2020 - PMB, DE 19 DE MAIO DE 2020, RETIFICADO PELO DECRETO Nº 96.503/2020 - PMB, DE 16/06/2020 | S14: 05/2023 - CME, DE 12/04/2023 | T14: 46854 | U14: AMANDA FERREIRA DA COSTA SA | V14: 982683788 | W14: 0348520- 018 | Z14: 46265
A15: DABEL | B15: MARCO | C15: MUNICIPAL | D15: 15040968 | E15: ESCOLA MUNICIPAL RUY DA SILVEIRA BRITTO | F15: ATIVA | G15: SEDE | H15: DABEL | I15: MUNICIPAL | J15: PROPRIA | K15: URBANA | L15: TRAVESSA DOUTOR ENEAS PINHEIRO | M15: 2871 | N15: ENTRE PERIMETRAL E JOAO PAULO II | O15: 66095015 | Q15: ruydasilveirabrito@semec.belem.pa.gov.br | S15: 04/2023 - CME, DE 12/04/2023 | T15: 46854 | U15: ROSEANE CONCEIÇÃO COUTO VOGADO | V15: 991890167 | W15: 1861417- 010 | X15: RONALDO XAVIER DE CARVALHO | Y15: 1882457-010 | Z15: 46265
A16: DABEL | B16: NAZARE | C16: MUNICIPAL | D16: 15176487 | E16: CENTRO DE REFERENCIA DE EDUCACAO INFANTIL PROF ORLANDO BITAR | F16: ATIVA | G16: SEDE | H16: DABEL | I16: MUNICIPAL | J16: PROPRIO | K16: URBANA | L16: AVENIDA GOVERNADOR JOSE MALCHER | M16: 793 | N16: ENTRE TV VISCONDE DE SOUZA FRANCO E TV QUINTINO BO | O16: 66055260 | Q16: crei.orlandobitar@semec.belem.pa.gov.br | S16: NÃO LOCALIZADO NO SITE DO CME BELÉM | U16: EDELRA DE JESUS NUNES DOS SANTOS | V16: 981158733 | W16: 0411353- 012 | Z16: 46265
A17: DABEL | B17: NAZARE | C17: OSC/CONVENIADA | D17: 15041743 | E17: INSTITUTO FELIPE SMALDONE BELEM | F17: ATIVA | G17: ESCOLA | H17: DABEL | I17: CEDIDO | J17: SUBVENÇÃO | K17: URBANA | L17: TRAVESSA QUATORZE DE MARCO | M17: 854 | O17: 66055490 | P17: 32229630 | R17: OSC - NÃO NECESSITA ATO DE CRIAÇÃO | S17: 048/2024 - CME, DE 11/12/2024 | T17: 47462 | Z17: 46265
A18: DABEL | B18: SAO BRAS | C18: OSC/CONVENIADA | D18: 15159477 | E18: CRECHE CASA LAR CORDEIRINHO DE DEUS | F18: ATIVA | G18: ESCOLA | H18: DABEL | I18: CEDIDO | J18: SUBVENÇÃO | K18: URBANA | L18: TRAVESSA FRANCISCO CALDEIRA CASTELO BRANCO | M18: 923 | O18: 66063000 | P18: 32497376 | R18: OSC - NÃO NECESSITA ATO DE CRIAÇÃO | S18: 39/2023 - CME, DE 13/12/2023 | T18: 46003 | Z18: 46265
A19: DABEL | B19: SAO BRAS | C19: MUNICIPAL | D19: 15040887 | E19: ESCOLA MUNICIPAL BENVINDA DE FRANCA MESSIAS | F19: ATIVA | G19: SEDE | H19: DABEL | I19: MUNICIPAL | J19: PROPRIA | K19: URBANA | L19: PRACA FLORIANO PEIXOTO | M19: 805 | O19: 66090290 | Q19: benvindadefrancamessias@semec.belem.pa.gov.br | S19: 025/2024 - CME, DE 19/06/2024 | T19: 47287 | U19: REGEANE CONCEIÇÃO ESTEVES DE LIMA | V19: 981144264 | W19: 0346535- 018 | X19: ELIETE DO SOCORRO KEMPER MAIA SOUZA | Y19: 0047287-012 | Z19: 46265
A20: DABEL | B20: SAO BRAS | C20: MUNICIPAL | D20: 15040909 | E20: ESCOLA MUNICIPAL ERNESTINA RODRIGUES | F20: ATIVA | G20: SEDE | H20: DABEL | I20: MUNICIPAL | J20: PROPRIA | K20: URBANA | L20: PASSAGEM ALBERTO ENGELHARD | M20: 286 | N20: PROX AO MUSEU EMILIO GOELD ENTRE MAGALHAES BARATA E GOV. JOSE MALCHER | O20: 66040520 | Q20: ernestinarodrigues@semec.belem.pa.gov.br | S20: 11/2026 - CME, DE 09/06/2026 | T20: 46546 | U20: CARLOS ALBERTO DOS SANTOS RAMOS | V20: 985805523 | W20: 1964267- 010 | X20: RAQUEL RODRIGUES DE MATOS VENTURA | Y20: 1983083-019 | Z20: 46265
A21: DABEL | B21: SAO BRAS | C21: MUNICIPAL | D21: 15040801 | E21: ESCOLA MUNICIPAL FRANCISCO DA SILVA NUNES | F21: ATIVA | G21: SEDE | H21: DABEL | I21: MUNICIPAL | J21: PROPRIO | K21: URBANA | L21: TRAVESSA FRANCISCO CALDEIRA CASTELO BRANCO | M21: 1824 | N21: SAO BRAZ PARIQUIS E CARIPUNAS | O21: 66063223 | Q21: franciscodasilvanunes@semec.belem.pa.gov.br | S21: 10/2025 - CME, DE 17/06/2025 | T21: 47650 | U21: ELIANA MARIA FERREIRA RIBEIRO MALATO | V21: 981570042 | W21: 0289426- 022 | X21: REGINA CELIA MELO DOS SANTOS | Y21: 0394556-011 | Z21: 46265
A22: DABEL | B22: TERRA FIRME | C22: MUNICIPAL | D22: 15040887 | E22: ANEXO SOLAR ACALANTO DA EM BENVINDA DE FRANCA MESSIAS | F22: ATIVA | G22: ANEXO | H22: DABEL | I22: MUNICIPAL | J22: ALUGUEL | K22: URBANA | L22: PASSAGEM INDEPENDENCIA | M22: 217 | N22: CONJ RESIDENCIAL RORAIMA | O22: 66070240 | S22: 025/2024 - CME, DE 19/06/2024 | T22: 47287 | U22: MAURICIO MAIA CERQUEIRA FILHO | V22: 982799894 | W22: 0346691- 010 | Z22: 46265
A23: DABEN | B23: BENGUI | C23: OSC/CONVENIADA | D23: 15174603 | E23: CENTRO COMUNITARIO NOSSA SENHORA DO PERPETUO SOCORRO | F23: ATIVA | G23: ESCOLA | H23: DABEL | I23: CEDIDO | J23: SUBVENÇÃO | K23: URBANA | L23: RUA OLAVO NUNES | M23: 74 | O23: 66630315 | P23: 32851977 | R23: OSC - NÃO NECESSITA ATO DE CRIAÇÃO | S23: 37/2023 - CME, DE 12/12/2023 | T23: 46003 | Z23: 46265
A24: DABEN | B24: BENGUI | C24: MUNICIPAL | D24: 15040640 | E24: ESCOLA MUNICIPAL AUGUSTO MEIRA FILHO | F24: ATIVA | G24: SEDE | H24: DABEN | I24: MUNICIPAL | J24: PROPRIA | K24: URBANA | L24: RUA LAMEIRA BITTENCOURT | M24: SN | N24: RUA SAO PEDRO E RUA BETANIA | O24: 66630010 | Q24: augusto-meiraf@semec.belem.pa.gov.br | R24: LEI Nº 7.183/1981 - PMB, DE 11/11/1981 | S24: 67/2019 - CME, DE 20/12/2019 | T24: 45242 | U24: ELIENE CAROLINA CHUCRE MACIEL ALBUQUERQUE | V24: 984297904 | W24: 0373478- 011 | X24: RODRIGO GOMES CEZAR DE SOUSA | Y24: 0427004-012 | Z24: 46265
A25: DABEN | B25: BENGUI | C25: MUNICIPAL | D25: 15040704 | E25: ESCOLA MUNICIPAL MARIA AMORAS DE OLIVEIRA | F25: ATIVA | G25: SEDE | H25: DABEN | I25: MUNICIPAL | J25: PROPRIA | K25: URBANA | L25: PASSAGEM SAO PEDRO | M25: SN | N25: PROXIMO A AJAX DE OLIVEIRA | O25: 66630390 | Q25: mariaamorasdeoliveira@semec.belem.pa.gov.br | S25: 10/2026 - CME, DE 09/06/2026 | T25: 47277 | U25: LAURIMAR DE MATOS FARIAS | V25: 981726775 | W25: 0027995- 011 | X25: CARLOS ANTONIO DE SOUZA RODRRIGUES | Y25: 0390518-018 | Z25: 46265
A26: DABEN | B26: BENGUI | C26: MUNICIPAL | D26: 15543234 | E26: ESCOLA MUNICIPAL PROFESSORA ANGELICA DO CARMO SANTOS PAIVA | F26: ATIVA | G26: SEDE | H26: DABEN | I26: MUNICIPAL | J26: PROPRIA | K26: URBANA | L26: RUA SAO BENTO | M26: 70 | N26: PROX. MERCADO NOVO ENTRE MAJ MIGUEL E SANTA MARIA | O26: 66630030 | Q26: profangelicadocarmosantospaiva@semec.belem.pa.gov | R26: DECRETO Nº 95.488/2020 - PMB, DE 03 DE FEVEREIRO DE 2020 | S26: 19/2023 - CME, DE 18/10/2023 | T26: 47043 | U26: JOSILAINE PARAGUASSU PINTO DA SILVA | V26: 985470707 | W26: 0370894- 014 | Z26: 46265
A27: DABEN | B27: BENGUI | C27: MUNICIPAL | D27: 15170853 | E27: ESCOLA MUNICIPAL PROFESSORA GILVANIA MARCIA BARROS DA SILVA | F27: ATIVA | G27: SEDE | H27: DABEN | I27: MUNICIPAL | J27: PROPRIA | K27: URBANA | L27: RUA SAO CLEMENTE | M27: S/N | N27: PASSAGEM PRATINHA | O27: 66630080 | Q27: gilvaniamarciabarrosdasilva@semec.belem.pa.gov.br | R27: DECRETO Nº 89.868/2017 - PMB, DE 2 DE OUTUBRO DE 2017 | S27: 15/2025 - CME, DE 17/06/2025 | T27: 47650 | U27: ELAINE CRISTINE RODRIGUES PEREIRA MENDES | V27: 982942476 | W27: 0348236- 018 | Z27: 46265
A28: DABEN | B28: BENGUI | C28: OSC/CONVENIADA | D28: 15574172 | E28: INSTITUTO UNIDOS VENCEREMOS | F28: ATIVA | G28: ESCOLA | H28: DABEN | I28: CEDIDO | J28: SUBVENÇÃO | K28: URBANA | L28: PASSAGEM SAO JOSE | M28: 25294 | O28: 66630215 | P28: 32237547 | R28: OSC - NÃO NECESSITA ATO DE CRIAÇÃO | S28: 09/2025 - CME, DE 06/05/2025 | T28: 46512 | Z28: 46265
A29: DABEN | B29: CABANAGEM | C29: OSC/CONVENIADA | D29: 15173860 | E29: CENTRO EDUCACIONAL DE ENSINO INFANTIL MUNDO ENCANTADO | F29: ATIVA | G29: ESCOLA | H29: DABEN | I29: CEDIDO | J29: SUBVENÇÃO | K29: URBANA | L29: RUA SAO PAULO | M29: 30 | O29: 66625490 | P29: 83354855 | R29: OSC - NÃO NECESSITA ATO DE CRIAÇÃO | S29: 35/2023 - CME, DE 22/11/2023 | T29: 45982 | Z29: 46265
A30: DABEN | B30: CABANAGEM | C30: OSC/CONVENIADA | D30: 15182258 | E30: CENTRO EDUCACIONAL EU AMO EU CUIDO | F30: ATIVA | G30: ESCOLA | H30: DABEN | I30: CEDIDO | J30: SUBVENÇÃO | K30: URBANA | L30: ALAMEDA ADRIANO ANDRADE | M30: 6 | O30: 66625140 | R30: OSC - NÃO NECESSITA ATO DE CRIAÇÃO | S30: NÃO LOCALIZADO NO SITE DO CME BELÉM | Z30: 46265
A31: DABEN | B31: CABANAGEM | C31: MUNICIPAL | D31: 15535827 | E31: ESCOLA MUNICIPAL DEPUTADO JOAO CARLOS BATISTA | F31: ATIVA | G31: SEDE | H31: DABEN | I31: MUNICIPAL | J31: PROPRIA | K31: URBANA | L31: TRAVESSA CRISTINA CARDOSO | M31: S/N | N31: ENTRE AV INDEPENDENCIA E RUA BELEM | O31: 66625630 | Q31: deputadojoaocarlosbatista@semec.belem.pa.gov.br | S31: 040/2024 - CME, DE 23/10/2024 | T31: 47413 | U31: MARIA GORETTI DE JESUS CARNEIRO | V31: 991114184 | W31: 0048550- 035 | X31: SILVANA PIMENTEL BORGES | Y31: 2008394-012 | Z31: 46265
A32: DABEN | B32: COQUEIRO | C32: MUNICIPAL | D32: 15181642 | E32: ESCOLA MUNICIPAL ALANA DE SOUZA BARBOSA I | F32: ATIVA | G32: SEDE | H32: DABEN | I32: MUNICIPAL | J32: ALUGUEL | K32: URBANA | L32: ALAMEDA PRIMAVERA | M32: 20 | N32: CONJ ARIRI BOLONHA QUADRA 26 RL 09 L 22 | O32: 66650507 | Q32: alanadesouzabarboza1@semec.belem.pa.gov.br | R32: DECRETO N.º 113.730/2025 – PMB, DE 23 DE JUNHO DE 2025 | S32: 22/2025 - CME, DE 09/09/2025 | T32: 46273 | U32: KATIANE DO ROSARIO CORREA BARBOSA | V32: 988079826 | W32: 0273511- 025 | X32: ROSANGELA VIEIRA DE ARAUJO | Y32: 1996843-017 | Z32: 46265
A33: DABEN | B33: COQUEIRO | C33: MUNICIPAL | D33: 15181863 | E33: ESCOLA MUNICIPAL ALANA DE SOUZA BARBOSA II | F33: ATIVA | G33: SEDE | H33: DABEN | I33: MUNICIPAL | J33: ALUGUEL | K33: URBANA | L33: RUA ESPERANTISTA | M33: 4 | O33: 66650600 | Q33: escolaanexa2alana@gmail.com | R33: DECRETO N.º 113.731/2025 – PMB, DE 23 DE JUNHO DE 2025 | S33: 22/2025 - CME, DE 09/09/2025 | T33: 46273 | U33: SANDRA MARIA PANTOJA PINTO | V33: 984115800 | W33: 0351644- 016 | X33: REGIANE RIBEIRO TEÓFILO | Y33: 0423351-028 | Z33: 46265
A34: DABEN | B34: COQUEIRO | C34: MUNICIPAL | D34: 15181685 | E34: ESCOLA MUNICIPAL CRISTO REDENTOR | F34: ATIVA | G34: SEDE | H34: DABEN | I34: MUNICIPAL | J34: ALUGUEL | K34: URBANA | L34: PASSAGEM COMERCIARIOS | M34: 108 | O34: 66650550 | Q34: cristoredentor@semec.belem.pa.gov.br | R34: DECRETO N.º 113.720/2025 – PMB, DE 23 DE JUNHO DE 2025 | S34: 22/2025 - CME, DE 09/09/2025 | T34: 46273 | U34: SHEILA ALVES DE ARAUJO | V34: 986505858 | W34: 0574058- 010 | X34: IRENILDA MONTEIRO MCHADO | Y34: 0431699-011 | Z34: 46265
A35: DABEN | B35: COQUEIRO | C35: MUNICIPAL | D35: 15169979 | E35: ESCOLA MUNICIPAL PADRE BRUNO SECHI | F35: ATIVA | G35: SEDE | H35: DABEN | I35: MUNICIPAL | J35: PROPRIA | K35: URBANA | L35: TRAVESSA WE 8 | M35: S/N | N35: AO LADO DA UNIDADE DE SAUDE | O35: 66670220 | Q35: pebrunosechi@semec.belem.pa.gov.br | R35: DECRETO Nº 113.110/2024 - PMB, DE 23 DE DEZEMBRO DE 2024 | S35: 22/2025 - CME, DE 09/09/2025 | T35: 46273 | U35: VANESSA MACHADO DE ANDRADE | V35: 982094242 | W35: 0347205- 011 | X35: NEMESIO LOPES MONTEIRO JUNIOR | Y35: 1836340-017 | Z35: 46265
A36: DABEN | B36: COQUEIRO | C36: MUNICIPAL | D36: 15223000 | E36: ESCOLA MUNICIPAL PROFESSORA ALANA DE SOUZA BARBOZA | F36: ATIVA | G36: SEDE | H36: DABEN | I36: MUNICIPAL | J36: PROPRIA | K36: URBANA | L36: QUADRA VINTE E SETE | N36: ESQ ESPERANTISTA | O36: 66650185 | Q36: alanasouzabarboza@semec.belem.pa.gov.br | R36: PORTARIA Nº. 1.313/2008 - GABS, DE 08 DE OUUBRO DE 2008 | S36: 042/2024 - CME, DE 23/10/2024 | T36: 47413 | U36: EULINA DOMINGUES LOPES | V36: 985382828 | W36: 0411310- 011 | X36: LIA DA COSTA TAVARES ATAIDE | Y36: 0391050-010 | Z36: 46265
A37: DABEN | B37: COQUEIRO | C37: MUNICIPAL | D37: 15164160 | E37: ESCOLA MUNICIPAL SAO GASPAR | F37: ATIVA | G37: SEDE | H37: DABEN | I37: MUNICIPAL | J37: ALUGUEL | K37: URBANA | L37: RUA B | M37: 61 | N37: CONJUNTO PEDRO TEIXEIRA EM FRENTE A ESCOLA 7 ANOS | O37: 66670070 | Q37: saogaspar@semec.belem.pa.gov.br | R37: PORTARIA Nº. 1.030/2014 - GABS, DE 23 DE ABRIL DE 2014 | S37: 12/2025 - CME, DE 17/06/2025 | T37: 47650 | U37: GIRLANE LOURENÇO DOS SANTOS | V37: 982444884 | W37: 0410551- 015 | Z37: 46265
A38: DABEN | B38: COQUEIRO | C38: MUNICIPAL | D38: 15558363 | E38: ESCOLA MUNICIPAL SILVIO LEANDRO | F38: ATIVA | G38: SEDE | H38: DABEN | I38: MUNICIPAL | J38: PROPRIA | K38: URBANA | L38: RODOVIA MARIO COVAS | M38: SN | N38: ESQ PASSAGEM COIMBRA | O38: 66670000 | Q38: silvioleandro@semec.belem.pa.gov.br | S38: 012/2024 - CME, DE 15/05/2024 | T38: 46887 | U38: PAULA ROBERTA DE JESUS MONTEIRO | V38: 982284941 | W38: 0422754- 013 | X38: DOMINGAS RAQUEL GONÇALVES MEDEIROS | Y38: 0390364-010 | Z38: 46265
A39: DABEN | B39: MANGUEIRAO | C39: OSC/CONVENIADA | D39: 15159469 | E39: ASSOCIACAO BENEFICENTE SAO CARLOS DO BRASIL | F39: ATIVA | G39: ESCOLA | H39: DABEN | I39: CEDIDO | J39: SUBVENÇÃO | K39: URBANA | L39: AVENIDA MANGUEIRAO | M39: 32 | O39: 66640480 | P39: 87291508 | R39: OSC - NÃO NECESSITA ATO DE CRIAÇÃO | S39: 32/2023 - CME, DE 22/11/2023 | T39: 45982 | Z39: 46265
A40: DABEN | B40: MANGUEIRAO | C40: MUNICIPAL | D40: 15543285 | E40: ESCOLA MUNICIPAL CATALINA I | F40: ATIVA | G40: SEDE | H40: DABEN | I40: MUNICIPAL | J40: PROPRIA | K40: URBANA | L40: TRAVESSA QUATRO | M40: SN | N40: CONJ. CATALINA | O40: 66640290 | Q40: catalina1@semec.belem.pa.gov.br | R40: PORTARIA Nº 547 / 2007 – PMB, DE 28 DE MAIO DE 2007 | S40: 24/2025 - CME, DE 21/10/2025 | T40: 47776 | U40: ROSANGELA ALBELIA RODRIGUES RABELO | V40: 983003058 | W40: 0248380- 036 | Z40: 46265
A41: DABEN | B41: MANGUEIRAO | C41: MUNICIPAL | D41: 15558347 | E41: ESCOLA MUNICIPAL CATALINA II | F41: ATIVA | G41: SEDE | H41: DABEN | I41: MUNICIPAL | J41: PROPRIA | K41: URBANA | L41: QUADRA NOVE | M41: SN | N41: AVENIDA CENTENARIO COM SG FAVARO CJ CATALINA | O41: 66640642 | Q41: catalina2@semec.belem.pa.gov.br | R41: PORTARIA Nº 548 / 2007 – PMB, DE 28 DE MAIO DE 2007 | S41: 08/2026 - CME, DE 09/06/2026 | T41: 48007 | U41: NAYARA ARAUJO DA COSTA FIGUEIREDO | V41: 989940628 | W41: 0566420- 015 | Z41: 46265
A42: DABEN | B42: MANGUEIRAO | C42: MUNICIPAL | D42: 15152324 | E42: ESCOLA MUNICIPAL CATALINA III | F42: ATIVA | G42: SEDE | H42: DABEN | I42: MUNICIPAL | J42: PROPRIA | K42: URBANA | L42: TRAVESSA SARGENTO FAVARRO | M42: SN | N42: TV. 15 CEL. AVIADOR BRITO TRAVESSA 15 | O42: 66640200 | Q42: catalina3@semec.belem.pa.gov.br | R42: PORTARIA Nº 549 / 2007 – PMB, DE 28 DE MAIO DE 2007 | S42: 06/2024 - CME, DE 21/02/2024 | T42: 47169 | U42: SINARA BERNARDO DIAS | V42: 984184444 | W42: 0348880- 014 | Z42: 46265
A43: DABEN | B43: MANGUEIRAO | C43: MUNICIPAL | D43: 15043088 | E43: ESCOLA MUNICIPAL WALTER LEITE CAMINHA | F43: ATIVA | G43: SEDE | H43: DABEN | I43: MUNICIPAL | J43: PROPRIA | K43: URBANA | L43: AVENIDA MAJOR AVIADOR SILVA FILHO | M43: SN | N43: CJ CATALINA TENENTE AVIADOR BRITO | O43: 66640220 | Q43: emef.walterleite@semec.belem.pa.gov.br | S43: 13/2025 - CME, DE 17/06/2025 | T43: 47650 | U43: RUTE RAIOL COSTA | V43: 980165440 | X43: MARCIA REGINA SOUZA CORDEIRO | Y43: 1992031-018 | Z43: 46265
A44: DABEN | B44: MANGUEIRAO | C44: OSC/CONVENIADA | D44: 15171760 | E44: SISTEMA DE ENSINO INFANTIL PAULO GUILHERME TOMAZ | F44: ATIVA | G44: ESCOLA | H44: DABEN | I44: CEDIDO | J44: SUBVENÇÃO | K44: URBANA | L44: RUA CHICO MENDES | M44: 1157 | O44: 66640445 | P44: 82764412 | R44: OSC - NÃO NECESSITA ATO DE CRIAÇÃO | S44: 31/2023 - CME, DE 22/11/2023 | T44: 46017 | Z44: 46265
A45: DABEN | B45: PARQUE VERDE | C45: MUNICIPAL | D45: 15558304 | E45: ANEXO FLORESTAN FERNANDES DA EM FLORESTAN FERNANDES | F45: ATIVA | G45: ANEXO | H45: DABEN | I45: MUNICIPAL | J45: ALUGUEL | K45: URBANA | L45: PASSAGEM SARGENTO GETULIO | M45: 9 | O45: 66635815 | S45: 28/2019 - CME, DE 27/02/2019 | T45: 43887 | U45: VILMA SHEILA AMORAS CONTREIRA | V45: 996028924 | W45: 1861409- 017 | Z45: 46265
A46: DABEN | B46: PARQUE VERDE | C46: MUNICIPAL | D46: 15558304 | E46: ESCOLA MUNICIPAL FLORESTAN FERNANDES | F46: ATIVA | G46: SEDE | H46: DABEN | I46: MUNICIPAL | J46: PROPRIA | K46: URBANA | L46: PASSAGEM SARGENTO GETULIO | M46: 70 | N46: RUA YAMADA | O46: 66635815 | S46: 28/2019 - CME, DE 27/02/2019 | T46: 43887 | U46: EDIR DE SOUZA MORAES | V46: 983744312 | W46: 0557447- 020 | X46: BRUNA EMANOELLE DA SILVA MORGALHO | Y46: 0391042-017 | Z46: 46265
A47: DABEN | B47: PRATINHA - ICOARACI | C47: MUNICIPAL | D47: 15569632 | E47: ESCOLA MUNICIPAL CORDOLINA FONTELLES DE LIMA | F47: ATIVA | G47: SEDE | H47: DABEN | I47: MUNICIPAL | J47: PROPRIA | K47: URBANA | L47: RUA SAO VICENTE DE PAULA | M47: SN | N47: ENTRE ROD. ARTUR BERNARDES E RUA LIBERAL | O47: 66816010 | Q47: emeif.cordolinaflima@semec.pmb.pa.gov.br | S47: 33/2011 - CME, DE 21/12/2011 | T47: DEFINITIVO | U47: JOSE NAZARENO FIGUEIREDO E SILVA | V47: 982683204 | W47: 0347051- 014 | X47: VALDILENE GALDINO DA SILVA | Y47: 1882511-015 | Z47: 46265
A48: DABEN | B48: PRATINHA - ICOARACI | C48: MUNICIPAL | D48: 15161544 | E48: ESCOLA MUNICIPAL DUAS IRMAS BIANCA E ADRIELY | F48: ATIVA | G48: SEDE | H48: DABEN | I48: MUNICIPAL | J48: PROPRIA | K48: URBANA | L48: RUA DOROTHY | M48: SN | N48: ENTRE PASS. SAMAUMA E TRAV 11 DE FEV | O48: 66816193 | Q48: duasirmasbiancaeadriely@semec.belem.pa.gov.br | R48: DECRETO Nº. 73.552/2013 – PMB, 15 DE JANEIRO DE 2013, RETIFICADO PELO DECRETO Nº. 81.011/2014 – PMB, 15 DE OUTUBRO DE 2014 | S48: 26/2015 - CME, DE 11/11/2015 | T48: 43779 | U48: GUSTAVO MENDES | V48: 985890468 | X48: RENATO MACIEIRA FIGUEIREDO | Y48: 0427284-015 | Z48: 46265
A49: DABEN | B49: PRATINHA - ICOARACI | C49: MUNICIPAL | D49: 15166821 | E49: ESCOLA MUNICIPAL NOVA ALIANCA | F49: ATIVA | G49: SEDE | H49: DABEN | I49: MUNICIPAL | J49: PROPRIA | K49: URBANA | L49: PASSAGEM PROFETA ISAIAS | M49: 216 | N49: AO LADO DA CAIXA D AGUA RUA EM FRENTE AO CIABA | O49: 66816250 | Q49: novaalianca@semec.belem.pa.gov.br | R49: DECRETO Nº 80.450/2014-PMB, DE 11 DE AGOSTO DE 2014 | S49: 07/2022 - CME, DE 21/09/2022 | T49: 46650 | U49: CLAUDIA MARTINS GOMES | V49: 982789467 | W49: 0352390- 018 | X49: JOSE ANTONIO VAZ VILHENA | Y49: 0427241-014 | Z49: 46265
A50: DABEN | B50: PRATINHA - ICOARACI | C50: MUNICIPAL | D50: 15173844 | E50: ESCOLA MUNICIPAL PRATINHA | F50: ATIVA | G50: SEDE | H50: DABEN | I50: MUNICIPAL | J50: ALUGUEL | K50: URBANA | L50: RODOVIA ARTUR BERNARDES | M50: 199 | N50: EM FRENTE A FABRICA DA CERPA | O50: 66816000 | Q50: emei.pratinha@semec.belem.pa.gov.br | R50: DECRETO Nº 91.275/2018 - PMB, DE 21 DE MAIO DE 2018 | S50: 04/2014 - CME, DE 26/03/2014 | T50: 43184 | U50: MIRIAM AIDA DA SILVA SOARES | V50: 988113747 | W50: 0348678- 010 | Z50: 46265
A51: DABEN | B51: PRATINHA - ICOARACI | C51: MUNICIPAL | D51: 15547272 | E51: ESCOLA MUNICIPAL PRATINHA II | F51: ATIVA | G51: SEDE | H51: DABEN | I51: MUNICIPAL | J51: ALUGUEL | K51: URBANA | L51: RODOVIA ARTUR BERNARDES | M51: 199 | N51: EM FRENTE A CERPASA AP 101 102 | O51: 66816000 | Q51: uei.pratinha@semec.belem.pa.gov.br | R51: DECRETO N.º 113.734/2025 – PMB, DE 23 DE JUNHO DE 2025 | S51: 22/2025 - CME, DE 09/09/2025 | T51: 46273 | U51: VANIA DE FATIMA DE SOUZA NERY | V51: 986128046 | W51: 1923919- 021 | Z51: 46265
A52: DABEN | B52: PRATINHA - ICOARACI | C52: MUNICIPAL | D52: 15181774 | E52: ESCOLA MUNICIPAL SAO JOAO PAULO II | F52: ATIVA | G52: SEDE | H52: DABEN | I52: MUNICIPAL | J52: PROPRIA | K52: URBANA | L52: RODOVIA ARTUR BERNARDES | M52: 576 | N52: PASS. ENGELHARD | O52: 66816000 | Q52: ueisaojose@gmail.com | R52: DECRETO Nº 111.991/2024 - PMB, DE 13 DE AGOSTO DE 2024 | S52: NÃO LOCALIZADO NO SITE DO CME BELÉM | U52: FABIOLA CALDAS DOS SANTOS | V52: 982168443 | W52: 0363936- 025 | Z52: 46265
A53: DABEN | B53: SAO CLEMENTE | C53: MUNICIPAL | D53: 15170845 | E53: ESCOLA MUNICIPAL PROFESSORA CLEONICE OLIVEIRA CONCEICAO | F53: ATIVA | G53: SEDE | H53: DABEN | I53: MUNICIPAL | J53: PROPRIA | K53: URBANA | L53: RUA DEZESSEIS DE AGOSTO | M53: 102 | N53: ESQ C TV 4 RESIDENCIAL CAMPOS ELIZIOS | O53: 66643610 | Q53: profcleoniceoliveiraconceicao@semec.belem.pa.gov.b | R53: DECRETO Nº 89.867/2017 - PMB, DE 2 DE OUTUBRO DE 2017 | S53: NÃO LOCALIZADO NO SITE DO CME BELÉM | U53: LUANDA DA SILVA WANZELLER MAIA | V53: 982585512 | W53: 0372501- 010 | Z53: 46265
A54: DABEN | B54: TAPANA - ICOARACI | C54: OSC/CONVENIADA | D54: 15586022 | E54: ASSOCIACAO C DO BAIRRO DO TAPANA | F54: ATIVA | G54: ESCOLA | H54: DABEN | I54: CEDIDO | J54: SUBVENÇÃO | K54: URBANA | L54: RUA YAMADA | M54: 23 | O54: 66833605 | P54: 86018168 | R54: OSC - NÃO NECESSITA ATO DE CRIAÇÃO | S54: 013/2024 - CME, DE 15/05/2024 | T54: 46156 | Z54: 46265
A55: DABEN | B55: TAPANA - ICOARACI | C55: OSC/CONVENIADA | D55: 15174565 | E55: ASSOCIACAO DE MORADORES DO RESIDENCIAL BOM JESUS | F55: ATIVA | G55: ESCOLA | H55: DABEN | I55: CEDIDO | J55: SUBVENÇÃO | K55: URBANA | L55: RUA NOVA | M55: 17 | O55: 66825227 | R55: OSC - NÃO NECESSITA ATO DE CRIAÇÃO | S55: 38/2023 - CME, DE 13/12/2023 | T55: 46003 | Z55: 46265
A56: DABEN | B56: TAPANA - ICOARACI | C56: OSC/CONVENIADA | D56: 15096378 | E56: C C EDUC SAO FRANCISCO DE ASSIS | F56: ATIVA | G56: ESCOLA | H56: DABEN | I56: CEDIDO | J56: SUBVENÇÃO | K56: URBANA | L56: RUA ALMIRANTE TAMANDARE | M56: 2084 | O56: 66825260 | P56: 32786950 | R56: OSC - NÃO NECESSITA ATO DE CRIAÇÃO | S56: 42/2023 - CME, DE 13/12/2023 | T56: 46003 | Z56: 46265
A57: DABEN | B57: TAPANA - ICOARACI | C57: OSC/CONVENIADA | D57: 15182185 | E57: CSE MEU AMIGO JHON TAPANA OSC ANEXO INSTITUTO JUNTOS E ALIANCADOS | F57: ATIVA | G57: ANEXO | H57: DABEN | J57: SUBVENÇÃO | K57: URBANA | L57: RUA PRESIDENTE DUTRA | M57: 152 | O57: 66825050 | R57: OSC - NÃO NECESSITA ATO DE CRIAÇÃO | S57: NÃO LOCALIZADO NO SITE DO CME BELÉM | Z57: 46265
A58: DABEN | B58: TAPANA - ICOARACI | C58: MUNICIPAL | D58: 15043070 | E58: ESCOLA MUNICIPAL GABRIEL LAGE DA SILVA | F58: ATIVA | G58: SEDE | H58: DABEN | I58: MUNICIPAL | J58: PROPRIA | K58: URBANA | L58: RUA IRMA ADELAIDE | M58: SN | N58: RESIDENCIAL PARQUE UNIAO ENTRE RUA QUINTINO E CARLOS MARIGUELA | O58: 66830120 | Q58: gabriellagedasilva@semec.belem.pa.gov.br | S58: 17/2025 - CME, DE 17/06/2025 | T58: 47650 | U58: ROSANNY DO PERPETUO SOCORRO DE SOUZA LIMA | V58: 989551509 | W58: 0375675- 019 | X58: ROBERTA VALADARES BRITO | Y58: 1992527-016 | Z58: 46265
A59: DABEN | B59: TAPANA - ICOARACI | C59: MUNICIPAL | D59: 15563464 | E59: ESCOLA MUNICIPAL JOSE ALVES CUNHA | F59: ATIVA | G59: SEDE | H59: DABEN | I59: MUNICIPAL | J59: PROPRIA | K59: URBANA | L59: RUA SANTOS DOS SANTOS | M59: SN | N59: PASSAGEM OSEIAS | O59: 66825620 | Q59: josealvescunha@semec.belem.pa.gov.br | S59: 49/2018 - CME, DE 06/06/2018 | T59: 45082 | U59: DOMINGAS MACEDO PEREIRA | V59: 988093255 | W59: 0370584- 015 | X59: FABIO LIMA MONTEIRO | Y59: 1996860-019 | Z59: 46265
A60: DABEN | B60: TAPANA - ICOARACI | C60: MUNICIPAL | D60: 15043029 | E60: ESCOLA MUNICIPAL MARIA HELOISA DE CASTRO | F60: ATIVA | G60: SEDE | H60: DABEN | I60: MUNICIPAL | J60: PROPRIA | K60: URBANA | L60: ESTRADA DO TAPANA | M60: SN | N60: ESQUINA COM A 5 RUA RODOVIA DO TAPANA | O60: 66825010 | Q60: mariaheloisadecastro@semec.belem.pa.gov.br | S60: 28/2023 - CME, DE 22/11/2023 | T60: 47078 | U60: ARLENE FIGUEIREDO LAMEIRA | V60: 981032068 | W60: 0346098- 017 | X60: MARILENE DOS SANTOS MONTEIRO | Y60: 1836633-014 | Z60: 46265
A61: DABEN | B61: TAPANA - ICOARACI | C61: MUNICIPAL | D61: 15181979 | E61: ESCOLA MUNICIPAL NOSSA SENHORA APARECIDA | F61: ATIVA | G61: SEDE | H61: DABEN | I61: MUNICIPAL | J61: COMODATO | K61: URBANA | L61: RUA INDEPENDENCIA | M61: 1 | N61: PARQUE UNIAO | O61: 66830335 | Q61: upnossasenhoraaparecida@gmail.com | R61: DECRETO Nº 113.729/2025 - PMB, DE 23 DE JUNHO DE 2020 | S61: 22/2025 - CME, DE 09/09/2025 | T61: 46273 | U61: MARIA RAIMUNDA DIAS SANTAREM | V61: 985066674 | W61: 0041548- 019 | X61: ROSIVALDO GUERREIRO PINHEIRO | Y61: 1916459-029 | Z61: 46265
A62: DABEN | B62: TAPANA - ICOARACI | C62: MUNICIPAL | D62: 15167690 | E62: ESCOLA MUNICIPAL NOSSO LAR | F62: ATIVA | G62: SEDE | H62: DABEN | I62: MUNICIPAL | J62: COMODATO | K62: URBANA | L62: RUA PRESIDENTE CASTELO BRANCO | M62: 250 | N62: 3 RUA DO TAPANA ENTRE ROD. DO TAPANA E TRAV UBERABA | O62: 66825070 | Q62: nossolar@semec.belem.pa.gov.br | R62: DECRETO Nº. 81.565/2014 – PMB, 16 DE DEZEMBRO DE 2014 | S62: NÃO LOCALIZADO NO SITE DO CME BELÉM | U62: GISELLE DE NAZARE SANTOS OLIVEIRA | W62: 0410977- 012 | Z62: 46265
A63: DABEN | B63: TAPANA - ICOARACI | C63: MUNICIPAL | D63: 15237001 | E63: ESCOLA MUNICIPAL PROFESSORA ALDA EUTROPIO DE SOUZA | F63: ATIVA | G63: SEDE | H63: DABEN | I63: MUNICIPAL | J63: PROPRIA | K63: URBANA | L63: ALAMEDA SUCUPIRA | M63: SN | N63: ROD TAPANA KM 02 ENTRE RUA SAO CLEMENTE E RUA SUCUPIRA | O63: 66830680 | Q63: aldaeutropiodesouza@semec.belem.pa.gov.br | S63: 010/2023 - CME, DE 21/06/2023 | T63: 46924 | U63: TATIANE SANTOS DA SILVA | V63: 981537028 | W63: 0373753- 012 | X63: RUAN TAVARES FREIRES | Y63: 0390674-010 | Z63: 46265
A64: DABEN | B64: TAPANA - ICOARACI | C64: MUNICIPAL | D64: 15175570 | E64: ESCOLA MUNICIPAL PROFESSORA ALDAIR NERI LOPES | F64: ATIVA | G64: SEDE | H64: DABEN | I64: MUNICIPAL | J64: ALUGUEL | K64: URBANA | L64: ALAMEDA AMAZONIA | M64: 14 | N64: LOTEAMENTO ACAI PROX. A RUA DO RANARIO | O64: 66825285 | Q64: profaldairnerilopes@semec.belem.pa.gov.br | R64: DECRETO Nº 95.487/2020 - PMB, DE 03 DE FEVEREIRO DE 2020 | S64: NÃO LOCALIZADO NO SITE DO CME BELÉM | U64: SHEYLA PAULINE FREIRE DA SILVA | V64: 985005411 | W64: 0348317- 018 | Z64: 46265
A65: DABEN | B65: TAPANA - ICOARACI | C65: MUNICIPAL | D65: 15170829 | E65: ESCOLA MUNICIPAL PROFESSORA ELVIRA SACRAMENTO DE QUADROS | F65: ATIVA | G65: SEDE | H65: DABEN | I65: MUNICIPAL | J65: PROPRIA | K65: URBANA | L65: ALAMEDA J | M65: 100 | N65: CONJUNTO BOSQUE ARAGUAIA COMUNIDADE VITORIA | O65: 66825539 | Q65: elvirasacramentodequadros@semec.belem.pa.gov.br | R65: DECRETO Nº 87.368/2017 - PMB, DE 06 DE FEVEREIRO DE 2017 | S65: NÃO LOCALIZADO NO SITE DO CME BELÉM | U65: THAYS KARINA DA SILVA SOUSA | V65: 984549802 | W65: 0567175- 014 | Z65: 46265
A66: DABEN | B66: TAPANA - ICOARACI | C66: MUNICIPAL | D66: 15181901 | E66: ESCOLA MUNICIPAL PROFESSORA PERPETUO SOCORRO JESUS FIGUEIREDO | F66: ATIVA | G66: SEDE | H66: DABEN | I66: MUNICIPAL | J66: PROPRIA | K66: URBANA | L66: RUA ALMIRANTE TAMANDARE | M66: 1306 | O66: 66825260 | Q66: escola.perpetuo.socorro@semec.belem.pa.gov.br | R66: DECRETO Nº 97.641/2020 - PMB, DE 26 DE OUTUBRO DE 2020 | S66: 22/2025 - CME, DE 09/09/2025 | T66: 46273 | U66: PRISCILLA DE CASSIA ARAUJO MOURA | V66: 982043891 | W66: 0450707- 024 | X66: JANEIDE FARIAS DIAS | Y66: 0421901-012 | Z66: 46265
A67: DABEN | B67: UNA | C67: MUNICIPAL | D67: 15181723 | E67: ESCOLA MUNICIPAL NOVA ESPERANCA | F67: ATIVA | G67: SEDE | H67: DABEN | I67: MUNICIPAL | J67: ALUGUEL | K67: URBANA | L67: RODOVIA TRANSCOQUEIRO | M67: 65 | O67: 66652300 | Q67: anexonovaesperanca@gmail.com | R67: DECRETO Nº 113.725/2025 - PMB, DE 23 DE JUNHO DE 2020 | S67: 22/2025 - CME, DE 09/09/2025 | T67: 46273 | U67: ANA PAULA DA SILVA CARNEIRO | V67: 984190069 | W67: 0346705- 029 | Z67: 46265
A68: DAENT | B68: AGUAS LINDAS | C68: OSC/CONVENIADA | D68: 15175626 | E68: CRECHE ESCOLA IRIS CRIANCAS AOS OLHOS DE DEUS | F68: ATIVA | G68: ESCOLA | H68: DABEN | I68: CEDIDO | J68: SUBVENÇÃO | K68: URBANA | L68: RUA OITO DE MARCO | M68: 41 B | O68: 66690200 | R68: OSC - NÃO NECESSITA ATO DE CRIAÇÃO | S68: 18/2023 - CME, DE 18/10/2023 | T68: 45947 | Z68: 46265
A69: DAENT | B69: AGUAS LINDAS | C69: MUNICIPAL | D69: 15167488 | E69: ESCOLA MUNICIPAL JARDIM NOVA VIDA | F69: ATIVA | G69: SEDE | H69: DAENT | I69: MUNICIPAL | J69: PROPRIA | K69: URBANA | L69: RUA DO FIO | M69: 83 | N69: RESIDENCIAL JARDIM NOVA VIDA | O69: 66690796 | R69: DECRETO Nº 85.697/2016 - PMB, DE 9 DE MAIO DE 2016 | S69: NÃO LOCALIZADO NO SITE DO CME BELÉM | U69: ELAINE CRISTINA DO NASCIMENTO SILVA | V69: 984331944 | W69: 0347680- 011 | Z69: 46265
A70: DAENT | B70: AGUAS LINDAS | C70: MUNICIPAL | D70: 15181847 | E70: ESCOLA MUNICIPAL MARIA DA CONCEICAO DE SOUZA | F70: ATIVA | G70: SEDE | H70: DAENT | I70: MUNICIPAL | J70: PROPRIA | K70: URBANA | L70: RUA OITO DE MARCO | M70: S/N | N70: CJ NOVA VIDA RUA WANDERLEI BELEM PROXIMO AO LINHO DO CONJUNTO JARDIM NOVA VIDAVID | O70: 66690200 | Q70: mariaconceicaodesouza@semec.belem.pa.gov.br | R70: DECRETO Nº 111.987/2024 - PMB, DE 13 DE AGOSTO DE 2024 | S70: 02/2025 - CME, DE 06/05/2025 | T70: 47608 | U70: GLAUCILENE SANTOS DA SILVA | V70: 980869992 | W70: 0349879- 010 | Z70: 46265
A71: DAENT | B71: AGUAS LINDAS | C71: MUNICIPAL | D71: 15573826 | E71: ESCOLA MUNICIPAL OLGA BENARIO | F71: ATIVA | G71: SEDE | H71: DAENT | I71: MUNICIPAL | J71: PROPRIA | K71: URBANA | L71: RUA ROSA DE LUXEMBURGO | M71: SN | N71: LOTEAMENTO OLGA BENARIO RUA DOS CABANOS E CARLOS PRESTES | O71: 66690190 | Q71: olgabenario@semec.belem.pa.gov.br | S71: 27/2020 - CME, DE 18/11/2020 | T71: 45958 | U71: OCIMAR MARCELO SOUZA DE CARVALHO | V71: 981240156 | W71: 1895125- 011 | X71: WESLEY JOSE BORGES SOARES | Y71: 0391182-013 | Z71: 46265
A72: DAENT | B72: AGUAS LINDAS | C72: MUNICIPAL | D72: 15161560 | E72: ESCOLA MUNICIPAL PARQUE BOLONHA | F72: ATIVA | G72: SEDE | H72: DAENT | I72: MUNICIPAL | J72: PROPRIA | K72: URBANA | L72: RUA OITO DE MARCO | M72: SN | N72: CONJUNTO VERDEJANTE 3 RUA DA MATA QUADRA XVI E XV | O72: 66690200 | Q72: parquebolonha@semec.belem.pa.gov.br | R72: DECRETO Nº 72.135/2012-PMB, DE 08 DE NOVEMBRO DE 2012 | S72: 09/2019 - CME, DE 04/01/2019 | T72: 45066 | U72: ALCEMIR PANTOJA RODRIGUES | V72: 991648904 | W72: 0320765- 024 | X72: ELMAR MOTA JANSEN FILHO | Y72: 0391166-018 | Z72: 46265
A73: DAENT | B73: AGUAS LINDAS | C73: MUNICIPAL | D73: 15166813 | E73: ESCOLA MUNICIPAL VERDEJANTE | F73: ATIVA | G73: SEDE | H73: DAENT | I73: MUNICIPAL | J73: ALUGUEL | K73: URBANA | L73: RUA OSVALDO CRUZ | M73: 45 | N73: CONJUNTO VERDEJANTE QUADRA 2 | O73: 66690395 | Q73: luciana.sousa@hotmail.com.br | R73: PORTARIA Nº. 0157/2015 - GABS, DE 23 DE FEVEREIRO DE 2015 | S73: NÃO LOCALIZADO NO SITE DO CME BELÉM | U73: LUCIANA CARVALHO DE SOUSA SABIO RAMOS | V73: 992086034 | W73: 0372706- 010 | Z73: 46265
A74: DAENT | B74: AGUAS LINDAS | C74: MUNICIPAL | D74: 15181880 | E74: ESCOLA MUNICIPAL VERDEJANTE I | F74: ATIVA | G74: SEDE | H74: DANET | I74: MUNICIPAL | J74: ALUGUEL | K74: URBANA | L74: QUADRA QUATRO | M74: 7 | N74: CONJUNTO VERDEJANTE I RUA E JARDIM NOVA VIDA | O74: 66690450 | Q74: escolaverdejante1@semec.pmb.pa.gov.br | R74: DECRETO N.º 113.727/2025 – PMB, DE 23 DE JUNHO DE 2025 | S74: 22/2025 - CME, DE 09/09/2025 | T74: 46273 | U74: SUELLEN FARIAS DOS SANTOS | V74: 983590264 | W74: 0350508- 011 | X74: MARIA DO SOCORRO DOS SANTOS PINHEIRO | Y74: 0392677-016 | Z74: 46265
A75: DAENT | B75: AURA | C75: MUNICIPAL | D75: 15167380 | E75: ESCOLA MUNICIPAL SANTANA DO AURA | F75: ATIVA | G75: SEDE | H75: DAENT | I75: MUNICIPAL | J75: PROPRIA | K75: URBANA | L75: ESTRADA SANTANA DO AURA | M75: SN | N75: LOTEAMENTO PARK AURA | O75: 66691010 | Q75: santanadoaura@semec.belem.pa.gov.br | R75: DECRETO Nº 82.593/2015 - PMB, DE 20 DE ABRIL DE 2015 | S75: 36/2024 - CME, DE 23/10/2024 | T75: 47413 | U75: CARINE FABIANE COELHO FIGUEIREDO | V75: 983147289 | W75: 0428280- 013 | X75: DILMA ROSA DOS REMEDIOS | Y75: 0390852-015 | Z75: 46265
A76: DAENT | B76: CASTANHEIRA | C76: MUNICIPAL | D76: 15563472 | E76: ANEXO ARIANA LIVIA AMOEDO DE CASTRO DA EM PROFESSORA TEREZINHA SOUZA | F76: ATIVA | G76: ANEXO | H76: DAENT | I76: CEDIDO | J76: ALUGUEL | K76: URBANA | L76: RUA JOSE ASSEGAWA | M76: 143 | N76: RUA JOSE HASSEGAWA | O76: 66645070 | R76: DECRETO Nº 111.990/2024 - PMB, DE 13 DE AGOSTO DE 2024 | S76: 22/2023 - CME, DE 18/10/2023 | T76: 47043 | U76: DANIELY SENA DOS SANTOS | V76: 988082333 | W76: 0347817- 017 | Z76: 46265
A77: DAENT | B77: CASTANHEIRA | C77: OSC/CONVENIADA | D77: 15182452 | E77: CENTRO EDUCACIONAL FAROL DO SABER | F77: ATIVA | G77: ESCOLA | H77: DAENT | I77: CEDIDO | J77: SUBVENÇÃO | K77: URBANA | L77: RODOVIA BR 316 | M77: 3262 | O77: 66645000 | R77: OSC - NÃO NECESSITA ATO DE CRIAÇÃO | S77: NÃO LOCALIZADO NO SITE DO CME BELÉM | Z77: 46265
A78: DAENT | B78: CASTANHEIRA | C78: MUNICIPAL | D78: 15563472 | E78: ESCOLA MUNICIPAL PROFESSORA TEREZINHA SOUZA | F78: ATIVA | G78: SEDE | H78: DAENT | I78: MUNICIPAL | J78: PROPRIA | K78: URBANA | L78: RUA JOSE ASSEGAWA | M78: 28 | N78: BR 316 | O78: 66645070 | Q78: profterezinhasouza@semec.belem.pa.gov.br | S78: 22/2023 - CME, DE 18/10/2023 | T78: 47043 | U78: SANDRA SUELY DA SILVA GOMES | V78: 982032001 | W78: 0350281- 017 | X78: JACINEIDE DE FATIMA OLIVEIRA SILVA | Y78: 1915088-019 | Z78: 46265
A79: DAENT | B79: CASTANHEIRA | C79: MUNICIPAL | D79: 15152316 | E79: ESCOLA MUNICIPAL ROSEMARY JORGE | F79: ATIVA | G79: SEDE | H79: DAENT | I79: MUNICIPAL | J79: PROPRIA | K79: URBANA | L79: RUA MARIANO | M79: 250 | N79: JOAO PAULO II E BR316 | O79: 66645415 | Q79: uei.rosemaryjorge@semec.pa.gov.br | R79: PORTARIA Nº 555 / 2007 – PMB, DE 28 DE MAIO DE 2007 | S79: 11/2025 - CME, DE 17/06/2025 | T79: 47650 | U79: ANA CARLA SOUSA FREIRE DE ARAUJO | V79: 982080867 | W79: 0352080- 019 | Z79: 46265
A80: DAENT | B80: CURIO-UTINGA | C80: OSC/CONVENIADA | D80: 15182754 | E80: CSE MEU AMIGO JHON CURIO UTINGA OSC ANEXO INSTITUTO ACELERA AMAZONIA | F80: ATIVA | G80: ANEXO | H80: DAENT | I80: CEDIDO | J80: SUBVENÇÃO | K80: URBANA | L80: AVENIDA JOAO PAULO II | M80: 2212 | O80: 66610770 | R80: OSC - NÃO NECESSITA ATO DE CRIAÇÃO | S80: NÃO LOCALIZADO NO SITE DO CME BELÉM | Z80: 46265
A81: DAENT | B81: CURIO-UTINGA | C81: MUNICIPAL | D81: 15558355 | E81: ESCOLA MUNICIPAL JESUS MARIA E JOSE | F81: ATIVA | G81: SEDE | H81: DAENT | I81: MUNICIPAL | J81: PROPRIA | K81: URBANA | L81: PASSAGEM ALBERTO ENGELHARD | M81: 79 | O81: 66610330 | Q81: jesusmariaejose@semec.belem.pa.gov.br | R81: PORTARIA Nº 557 / 2007 – PMB, DE 28 DE MAIO DE 2007 | S81: 26/2025 - CME, DE 21/10/2025 | T81: 47776 | U81: LORENA THAIS COSTA CAMPOS | V81: 981074041 | W81: 0566586- 010 | Z81: 46265
A82: DAENT | B82: CURIO-UTINGA | C82: MUNICIPAL | D82: 15577767 | E82: ESCOLA MUNICIPAL WILSON BAHIA DE SOUZA | F82: ATIVA | G82: SEDE | H82: DAENT | I82: MUNICIPAL | J82: PROPRIA | K82: URBANA | L82: PASSAGEM CRUZEIRO | M82: S/N | N82: ESQUINA DA JOAO PAULO II | O82: 66610755 | Q82: wilsonbahidadesouza@semec.belem.pa.gov.br | R82: PORTARIA Nº 558 / 2007 – PMB, DE 28 DE MAIO DE 2007 | S82: 026/2024 - CME, DE 19/06/2024 | T82: 47287 | U82: MARIA PAULA FERREIRA MAIA DA SILVA | V82: 989264318 | W82: 0348449- 011 | Z82: 46265
A83: DAENT | B83: MARACANGALHA | C83: MUNICIPAL | D83: 15043592 | E83: ESCOLA MUNICIPAL PROFESSORA IDA OLIVEIRA | F83: ATIVA | G83: SEDE | H83: DAENT | I83: MUNICIPAL | J83: PROPRIA | K83: URBANA | L83: RUA ONZE | M83: SN | N83: CONJUNTO PROVIDENCIA ENTRE AVENIDA NORTE E AVENIDA SUL | O83: 66110410 | Q83: profidadeoliveira@semec.belem.pa.gov.br | S83: 32/2025 - CME, DE 19/12/2025 | T83: 47835 | U83: ADNILDO PINHEIRO WANZELLER | V83: 983608116 | W83: 0346063- 019 | X83: MARIA LUCIA QUEIROZ ARRUDA | Y83: 2031876-010 | Z83: 46265
A84: DAENT | B84: MARACANGALHA | C84: MUNICIPAL | D84: 15589021 | E84: ESCOLA MUNICIPAL PROVIDENCIA | F84: ATIVA | G84: SEDE | H84: DAENT | I84: MUNICIPAL | J84: PROPRIO | K84: URBANA | L84: AVENIDA SUL | M84: SN | N84: NA FEIRA CJ PROVIDENCIA | O84: 66110071 | Q84: uei.providencia@semec.belem.pa.gov.br | R84: PORTARIA Nº 559 / 2007 – PMB, DE 28 DE MAIO DE 2007 | S84: 07/2023 - CME, DE 12/04/2023 | T84: 46854 | U84: RENATA MAC DOWELL RIBEIRO | V84: 987252756 | W84: 0573965- 013 | Z84: 46265
A85: DAENT | B85: MARAMBAIA | C85: MUNICIPAL | D85: 15142264 | E85: ESCOLA MUNICIPAL PALMIRA LINS DE CARVALHO | F85: ATIVA | G85: SEDE | H85: DAENT | I85: MUNICIPAL | J85: PROPRIA | K85: URBANA | L85: RUA F | M85: S/N | N85: CJ EUCLIDES FIGUEIREDO QD 3 | O85: 66620770 | Q85: palmiralinsdecarvalho@semec.belem.pa.gov.br | S85: 04/2026 CME, DE 28/04/2026 | T85: 47965 | U85: ROSILEA PANTOJA DOS SANTOS | V85: 981153691 | W85: 0175811- 016 | X85: ANA CLAUDIA SILVA DO VALE | Y85: 1992023-015 | Z85: 46265
A86: DAENT | B86: MARAMBAIA | C86: MUNICIPAL | D86: 15152332 | E86: ESCOLA MUNICIPAL PROFESSORA AURORA GUIMARES VIEIRA | F86: ATIVA | G86: SEDE | H86: DAENT | I86: MUNICIPAL | J86: PROPRIA | K86: URBANA | L86: ALAMEDA AGUA CRISTAL | M86: SN | N86: ENTRE RUA ANCHIETA E RUA ESPERANTO | O86: 66615032 | Q86: profaauroraguimaraesvieira@semec.belem.pa.gov.br | R86: DECRETO Nº 96.723/2020 - PMB, DE 20 DE JULHO DE 2020 | S86: NÃO LOCALIZADO NO SITE DO CME BELÉM | U86: MARY ANNE GAMA DE ALMADA | V86: 982465990 | W86: 0175900- 019 | Z86: 46265
A87: DAENT | B87: MARAMBAIA | C87: MUNICIPAL | D87: 15040992 | E87: ESCOLA MUNICIPAL REPUBLICA DE PORTUGAL | F87: ATIVA | G87: SEDE | H87: DAENT | I87: MUNICIPAL | J87: PROPRIA | K87: URBANA | L87: RUA ANCHIETA | M87: 359 | N87: ENTRE AVENIDA DALVA E CANAL AGUA CRISTAL | O87: 66615030 | Q87: republicadeportugal@semec.belem.pa.gov.br | S87: 03/2026 - CME, DE 28/04/2026 | T87: 47965 | U87: THIAGO AUGUSTO DE OLIVEIRA DA CONCEIÇÃO | V87: 981464070 | W87: 0373656- 025 | X87: SHIRLENE SOUSA DA NATIVIDADE | Y87: 0390534-013 | Z87: 46265
A88: DAENT | B88: MARAMBAIA | C88: MUNICIPAL | D88: 15181871 | E88: ESCOLA MUNICIPAL SANTA RITA DE CASSIA | F88: ATIVA | G88: SEDE | H88: DAENT | I88: MUNICIPAL | J88: ALUGUEL | K88: URBANA | L88: PASSAGEM JARBAS PASSARINHO | M88: 199 | N88: RUA DE MARINHA E RODOLFO CHERMONT | O88: 66620490 | Q88: anexo.santaritadecassia@semec.belem.pa.gov.br | R88: DECRETO N.º 113.724/2025 – PMB, DE 23 DE JUNHO DE 2025 | S88: 22/2025 - CME, DE 09/09/2025 | T88: 08/09/0206 | U88: JULY RAFAELA VASCONCELOS CESAR CALDAS | V88: 993506675 | W88: 0346381- 010 | Z88: 46265
A89: DAENT | B89: SOUZA | C89: MUNICIPAL | D89: 15168468 | E89: ESCOLA MUNICIPAL PAULO ALMEIDA BRASIL | F89: ATIVA | G89: SEDE | H89: DAENT | I89: MUNICIPAL | J89: PROPRIA | K89: URBANA | L89: PASSAGEM SANTA TERESINHA | M89: 11 | N89: CJ IMPERIO AMAZONICO | O89: 66613760 | Q89: emeif.palmeidabrasil@semec.pmb.pa.gov.br | R89: DECRETO Nº 86.315/2016 – PMB, DE 5 DE AGOSTO DE 2016 | S89: 034/2024 - CME, DE 23/10/2024 | T89: 47413 | U89: ERICA CRISTINA BARBOSA DA GAMA | V89: 988889459 | W89: 0158100- 018 | X89: JOSE RIBAMAR PESSOA DO NASCIMENTO | Y89: 0390577-014 | Z89: 46265
A90: DAGUA | B90: CANUDOS | C90: MUNICIPAL | D90: 15181669 | E90: ESCOLA MUNICIPAL SANTO AGOSTINHO DA ALDEIA | F90: ATIVA | G90: SEDE | H90: DAGUA | I90: MUNICIPAL | J90: ALUGUEL | K90: URBANA | L90: AVENIDA CIPRIANO SANTOS | M90: 583/587 | O90: 66070605 | Q90: santoagostinho@semec.belem.pa.gov.br | R90: DECRETO N.º 113.726/2025 – PMB, DE 23 DE JUNHO DE 2025 | S90: 22/2025 - CME, DE 09/09/2025 | T90: 46273 | U90: MARIA AMELIA DA COSTA BARBOSA | V90: 981180492 | W90: 0175781- 028 | X90: MARIA NAZARE MARINHO DA MOTA | Y90: 1862758-023 | Z90: 46265
A91: DAGUA | B91: CONDOR | C91: MUNICIPAL | D91: 15152030 | E91: ESCOLA MUNICIPAL ALLAN KARDEC | F91: ATIVA | G91: SEDE | H91: DAGUA | I91: MUNICIPAL | J91: COMODATO | K91: URBANA | L91: PASSAGEM ALLAN KARDEC | M91: 1894 | N91: AV ROBERTO CAMELIER | O91: 66033130 | Q91: uei.allankardec@semec.belem.pa.gov.br | R91: PORTARIA Nº 540 / 2007 – PMB, DE 28 DE MAIO DE 2007 | S91: 8/2019 CME, DE 04/01/2019 | T91: 45294 | U91: MAXIMIANA ANTONIA DA SILVA | V91: 981065291 | W91: 0348651- 015 | Z91: 46265
A92: DAGUA | B92: CONDOR | C92: MUNICIPAL | D92: 15040879 | E92: ESCOLA MUNICIPAL ANTONIO CARVALHO BRASIL | F92: ATIVA | G92: SEDE | H92: DAGUA | I92: MUNICIPAL | J92: PROPRIA | K92: URBANA | L92: AVENIDA ALCINDO CACELA | M92: 3743 | N92: PASSAGEM VINTE E UM DE ABRIL PASS ORQUIDEA | O92: 66065213 | Q92: antoniocarvalhobrasil@semec.belem.pa.gov.br | S92: 66/2018 - CME, DE 05/12/2018 | T92: 44886 | U92: CARMEM LUCIA SANTOS | X92: SILVIA LUCIA OLIVEIRA DA COSTA | Y92: 198808-011 | Z92: 46265
A93: DAGUA | B93: CONDOR | C93: MUNICIPAL | D93: 15040836 | E93: ESCOLA MUNICIPAL NESTOR NONATO LIMA | F93: ATIVA | G93: SEDE | H93: DAGUA | I93: MUNICIPAL | J93: PROPRIA | K93: URBANA | L93: QUADRA F | M93: SN | N93: CONJ RADIONAL II QUADRA F | O93: 66033085 | Q93: nestornonatodelima@semec.belem.pa.gov.br | S93: 33/2025 - CME, DE 19/12/2025 | T93: 47835 | U93: FERNANDO TEIXEIRA DA SILVA | V93: 986060194 | W93: 0427896- 010 | X93: MARIA DO SOCORRO MIRANDA MONTEIRO | Y93: 0047724-013 | Z93: 46265
A94: DAGUA | B94: CONDOR | C94: MUNICIPAL | D94: 15040976 | E94: ESCOLA MUNICIPAL SILVIO NASCIMENTO | F94: ATIVA | G94: SEDE | H94: DAGUA | I94: MUNICIPAL | J94: PROPRIA | K94: URBANA | L94: AVENIDA ALCINDO CACELA | M94: 4146 | N94: ESQUINA COM TV. APINAGES ENTRE TV. APINAGES E PASSAGEM PARINTINS | O94: 66065219 | Q94: silvionascimento@semec.belem.pa.gov.br | S94: 38/2018 - CME, DE 14/03/2018 | T94: 44998 | U94: GLAICE DA SILVA NASCIMENTO | V94: 989892905 | X94: JOSE ARLINDO ESTUMANO DA SILVA | Y94: 1895320-019 | Z94: 46265
A95: DAGUA | B95: CREMACAO | C95: MUNICIPAL | D95: 15167640 | E95: ESCOLA MUNICIPAL ENCANTO DO SABER | F95: ATIVA | G95: SEDE | H95: DAGUA | I95: MUNICIPAL | J95: ALUGUEL | K95: URBANA | L95: RUA DOS MUNDURUCUS | M95: 3476 | N95: ENT 9 DE JANEIRO E 3 DE MAIO | O95: 66040036 | Q95: uei.encantodosaber@semec.belem.pa.gov.br | R95: PORTARIA Nº. 2.064/2015 - GABS, DE 21/ DE JULHO DE 2015 | S95: 26/2023 - CME, DE 22/11/2023 | T95: 47078 | U95: CARLENE SIBELI SODRE DAMASCENO NAHUM | V95: 981995496 | W95: 0349216- 010 | Z95: 46265
A96: DAGUA | B96: CREMACAO | C96: MUNICIPAL | D96: 15181790 | E96: ESCOLA MUNICIPAL FRANCISCO DE ASSIS | F96: ATIVA | G96: SEDE | H96: DAGUA | I96: MUNICIPAL | J96: PROPRIO | K96: URBANA | L96: PASSAGEM SAO SILVESTRE | M96: 2005 | O96: 66065710 | Q96: franciscodeassis@semec.belem.gov.br | R96: DECRETO N.º 113.723/2025 – PMB, DE 23 DE JUNHO DE 2025 | S96: 22/2025 - CME, DE 09/09/2025 | T96: 46273 | U96: VALDILENE SOUZA FRANCO | V96: 981192665 | W96: 2009463- 018 | Z96: 46265
A97: DAGUA | B97: CREMACAO | C97: MUNICIPAL | D97: 15543382 | E97: ESCOLA MUNICIPAL VENUZINA MARINHO DE SOUZA | F97: ATIVA | G97: SEDE | H97: DAGUA | I97: MUNICIPAL | J97: PROPRIA | K97: URBANA | L97: AVENIDA ALCINDO CACELA | M97: 3015 | N97: AO LADO DO POSTO POLICIAL FERNANDO GUILHOM E SAO MIGUEL | O97: 66065205 | Q97: profvenuzinamarinhodesouza@semec.belem.pa.gov.br | R97: DECRETO Nº 95.218/2019 - PMB, DE 27 DE DEZEMBRO DE 2019 | S97: 012/2023 - CME, DE 21/06/2023 | T97: 46924 | U97: LUNA ALMEIDA RIBEIRO | V97: 981143940 | W97: 0346624- 010 | Z97: 46265
A98: DAGUA | B98: GUAMA | C98: OSC/CONVENIADA | D98: 15098338 | E98: ASSOCIACAO DE PAIS E EDUCADORES MOARANA | F98: ATIVA | G98: ESCOLA | H98: DAGUA | I98: CEDIDO | J98: SUBVENÇÃO | K98: URBANA | L98: TRAVESSA VINTE E CINCO DE JUNHO | M98: 329 | O98: 66075513 | P98: 32296480 | R98: OSC - NÃO NECESSITA ATO DE CRIAÇÃO | S98: 07/2024 - CME, DE 21/02/2024 | T98: 46073 | Z98: 46265
A99: DAGUA | B99: GUAMA | C99: OSC/CONVENIADA | D99: 15572137 | E99: ASSOCIACAO DOS MORADORES DO BAIRRO DO GUAMA | F99: ATIVA | G99: ESCOLA | H99: DAGUA | I99: CEDIDO | J99: SUBVENÇÃO | K99: URBANA | L99: PASSAGEM SAO CRISTOVAO | M99: 69 | O99: 66065670 | P99: 32696532 | R99: OSC - NÃO NECESSITA ATO DE CRIAÇÃO | S99: 015/2024 - CME, DE 15/05/2024 | T99: 46156 | Z99: 46265
A100: DAGUA | B100: GUAMA | C100: OSC/CONVENIADA | D100: 15098125 | E100: CENTRO CATEQUETICO DE PROMOCAO HUMANA SANTA IZABEL DA HUNGRIA | F100: ATIVA | G100: ESCOLA | H100: DAGUA | I100: CEDIDO | J100: SUBVENÇÃO | K100: URBANA | L100: PASSAGEM GUERRA PASSOS | M100: 442 | O100: 66073240 | P100: 32530133 | R100: OSC - NÃO NECESSITA ATO DE CRIAÇÃO | S100: 09/2024 - CME, DE 21/02/2023 | T100: 45708 | Z100: 46265
A101: DAGUA | B101: GUAMA | C101: MUNICIPAL | D101: 15040682 | E101: ESCOLA MUNICIPAL AMALIA PAUMGARTTEN | F101: ATIVA | G101: SEDE | H101: DAGUA | I101: MUNICIPAL | J101: PROPRIA | K101: URBANA | L101: PASSAGEM SANTA ROSA | M101: SN | N101: ENTRE PASS POPULAR E BERNARDO SAYAO ENTRE JOS BONIFCIO EBERNARDO SAYAO | O101: 66075530 | Q101: amaliapaungartten@semec.belem.pa.gov.br | S101: 011/2023 - CME, DE 21/06/2023 | T101: 46924 | U101: AUREA MARIA | V101: 985529484 | X101: ODILA FORMIGOSA SIQUEIRA | Y101: 0049603-019 | Z101: 46265
A102: DAGUA | B102: GUAMA | C102: MUNICIPAL | D102: 15167542 | E102: ESCOLA MUNICIPAL DIREITO DE SER CRIANCA | F102: ATIVA | G102: SEDE | H102: DAGUA | I102: MUNICIPAL | J102: ALUGUEL | K102: URBANA | L102: TRAVESSA TEOFILO CONDURU | M102: 900 | N102: AO LADO DO INSTITUTO MARIA E MARIAS ENTRE RUA DOS MUNDURUCUS E AV. CONSELHEIRO FURTADO | O102: 66073570 | Q102: direitodesercrianca@semec.belem.pa.gov.br | R102: DECRETO Nº 85.304/2016 - PMB, DE 22 DE MARÇO DE 2016 | S102: NÃO LOCALIZADO NO SITE DO CME BELÉM | U102: SUZELI ROBERTA OLIVEIRA FERREIRA | V102: 991972520 | W102: 0370711- 017 | X102: RODRIGO DOS SANTOS ROSARIO | Y102: 0391000-012 | Z102: 46265
A103: DAGUA | B103: GUAMA | C103: MUNICIPAL | D103: 15558282 | E103: ESCOLA MUNICIPAL EDSON LUIS | F103: ATIVA | G103: SEDE | H103: DAGUA | I103: MUNICIPAL | J103: PROPRIA | K103: URBANA | L103: RUA BARAO DE IGARAPE MIRI | M103: 1415 | N103: ENTRE AUGUSTO CORREA E RUA DA OLARIA UFPA | O103: 66075048 | Q103: edsonluis@semec.belem.pa.gov.br | S103: 014/2024 - CME, DE 15/05/2024 | T103: 47252 | U103: ALESSANDRA HELENA XAVIER TAVARES MIRANDA | V103: 980712262 | W103: 1923994- 015 | X103: ELIZANGELA ALMEIDA DA SILVA | Y103: 1991906-010 | Z103: 46265
...

Sheet DistritoBairro

Sheet Lista Mestra
A1: LISTA MESTRA — CHECKLIST DA DOCUMENTAÇÃO ESCOLAR
A2: Transcrição operacional integral dos 53 registros do Checklist da Coordenadoria de Documentação Escolar
A4: Os 41 itens técnicos recebem peso conforme a criticidade. Os 12 itens do Checklist da Visita têm natureza de síntese e peso zero, evitando a duplicação estatística dos mesmos controles.
A6: Código | B6: Seção do Checklist | C6: Documento/item de controle | D6: Evidência mínima | E6: Abrangência/periodicidade | F6: Criticidade | G6: Peso | H6: Origem no Checklist | I6: Responsável primário | J6: Orientação de conferência
A7: INS-01 | B7: 1. Documentos institucionais | C7: Ato de criação da escola | D7: Ato integral, legível e disponível para conferência. | E7: Vigência e anterior | F7: Crítica | G7: 3 | H7: Checklist CDE — item 1.1 | I7: Gestão/Secretaria | J7: Conferir número, data, órgão emissor e denominação da unidade.
A8: INS-02 | B8: 1. Documentos institucionais | C8: Recibo do Censo Escolar (Autorização) | D8: Recibo do Censo Escolar e comprovantes correspondentes. | E8: Vigência e anterior | F8: Alta | G8: 2 | H8: Checklist CDE — item 1.2 | I8: Secretaria | J8: Conciliar o recibo com o período, as matrículas, turmas e etapas declaradas.
A9: INS-03 | B9: 1. Documentos institucionais | C9: Ato de autorização, credenciamento ou reconhecimento | D9: Ato completo, vigente e compatível com as etapas/modalidades ofertadas. | E9: Vigência e anterior | F9: Crítica | G9: 3 | H9: Checklist CDE — item 1.3 | I9: Gestão | J9: Conferir número, data, vigência, órgão emissor e abrangência.
A10: INS-04 | B10: 1. Documentos institucionais | C10: Regimento Escolar atualizado | D10: Versão atualizada, aprovada, datada e disponível. | E10: Vigência e anterior | F10: Alta | G10: 2 | H10: Checklist CDE — item 1.4 | I10: Gestão | J10: Verificar aprovação, atualização e coerência com a organização escolar.
A11: INS-05 | B11: 1. Documentos institucionais | C11: Projeto Político-Pedagógico (PPP) | D11: PPP atualizado, aprovado e disponível. | E11: Vigência e anterior | F11: Alta | G11: 2 | H11: Checklist CDE — item 1.5 | I11: Gestão/Coordenação | J11: Conferir diagnóstico, objetivos, organização pedagógica, metas e atualização.
A12: INS-06 | B12: 1. Documentos institucionais | C12: Calendário Escolar vigente | D12: Calendário acessível no SIGA: Administração > Calendário Escolar > Acessar Calendário. | E12: Vigência e anterior | F12: Alta | G12: 2 | H12: Checklist CDE — item 1.6 | I12: Gestão/Secretaria | J12: Conferir aprovação, dias letivos, carga horária e eventuais reposições.
A13: INS-07 | B13: 1. Documentos institucionais | C13: Matriz curricular, inclusive cursos técnicos | D13: Matriz vigente por etapa/modalidade, com componentes e cargas horárias. | E13: Vigência e anterior | F13: Crítica | G13: 3 | H13: Checklist CDE — item 1.7 | I13: Coordenação/Secretaria | J13: Conciliar com horários, diários, resultados e documentos expedidos.
A14: SEC-01 | B14: 2. Secretaria escolar | C14: Livro de Matrícula | D14: Livro completo, atualizado e com termos de abertura e encerramento. | E14: Vigência e anterior | F14: Crítica | G14: 3 | H14: Checklist CDE — item 2.1 | I14: Secretaria | J14: Conciliar com fichas de matrícula, turmas e sistema informatizado.
A15: SEC-02 | B15: 2. Secretaria escolar | C15: Livro de Atas — resultados finais, Conselho de Classe, reuniões e outros | D15: Livros completos, sequenciais, datados e assinados. | E15: Vigência e anterior | F15: Crítica | G15: 3 | H15: Checklist CDE — item 2.2 | I15: Gestão/Secretaria | J15: Verificar resultados, deliberações, participantes, datas e assinaturas.
A16: SEC-03 | B16: 2. Secretaria escolar | C16: Livro de Registro de Diplomas e Certificados, quando aplicável | D16: Registro sequencial, íntegro e rastreável dos documentos expedidos. | E16: Vigência e anterior | F16: Crítica | G16: 3 | H16: Checklist CDE — item 2.3 | I16: Secretaria | J16: Conciliar numeração, estudante, curso, data e documento arquivado.
A17: SEC-04 | B17: 2. Secretaria escolar | C17: Protocolos de entrada e saída de documentos | D17: Registros cronológicos de recebimento, tramitação e entrega. | E17: Vigência e anterior | F17: Alta | G17: 2 | H17: Checklist CDE — item 2.4 | I17: Secretaria | J17: Conferir número, data, interessado, assunto, destino e recebimento.
A18: SEC-05 | B18: 2. Secretaria escolar | C18: Arquivo ativo e arquivo permanente organizados | D18: Pastas classificadas, preservadas, localizáveis e com acesso controlado. | E18: Vigência e anterior | F18: Crítica | G18: 3 | H18: Checklist CDE — item 2.5 | I18: Gestão/Secretaria | J18: Verificar integridade, ordenação, conservação, índice e proteção dos dados.
... A59: VIS-12 | B59: 7. Checklist da visita | C59: Dados do Censo Escolar conferidos | D59: Síntese de conferência da visita. | E59: Na visita | F59: Síntese | G59: 0 | H59: Checklist para a visita — item 12 | I59: Equipe de visita | J59: Conciliar dados declarados com os registros escolares.

Sheet Plano de Auditoria
A1: PLANO DE AUDITORIA DOCUMENTAL
A2: Programação, execução e consolidação das verificações por unidade educacional
A5: ID auditoria | B5: Unidade | C5: Distrito | D5: Tipo de verificação | E5: Prioridade | F5: Data planejada | G5: Data realizada | H5: Auditor(a)/equipe | I5: Situação | J5: Itens previstos | K5: Itens avaliados | L5: Índice ponderado | M5: NC críticas | N5: Checklist da visita concluído | O5: Observações
A6: AUD-001 | B6: ESCOLA MUNICIPAL PROFESSORA MARIA AUXILIADORA MARTINS GONCALVES | C6: {=IF(B6="","",IFERROR(INDEX('Cadastro Unidades'!$A$6:$A$222,MATCH(B6,'Cadastro Unidades'!$E$6:$E$222,0)),""))} -> DABEL | D6: Acompanhamento de pendências | E6: Alta | I6: Planejada | J6: =IF(A7="","",COUNTIF('Auditoria Documental'!$A$7:$A$1000,A7)) -> 0 | K6: =IF(A7="","",COUNTIFS('Auditoria Documental'!$A$7:$A$1000,A7,'Auditoria Documental'!$K$7:$K$1000,"<>Não avaliado",'Auditoria Documental'!$K$7:$K$1000,"<>")) -> 0 | L6: =IF(A7="","",IFERROR(SUMIFS('Auditoria Documental'!$N$7:$N$1000,'Auditoria Documental'!$A$7:$A$1000,A7)/SUMIFS('Auditoria Documental'!$M$7:$M$1000,'Auditoria Documental'!$A$7:$A$1000,A7),0)) -> 0 | M6: =IF(A7="","",COUNTIFS('Auditoria Documental'!$A$7:$A$1000,A7,'Auditoria Documental'!$J$7:$J$1000,3,'Auditoria Documental'!$K$7:$K$1000,"Não conforme")) -> 0 | N6: =IF(A7="","",IFERROR(COUNTIFS('Auditoria Documental'!$A$7:$A$1000,A7,'Auditoria Documental'!$G$7:$G$1000,"7. Checklist da visita",'Auditoria Documental'!$K$7:$K$1000,"<>Não avaliado",'Auditoria Documental'!$K$7:$K$1000,"<>")/COUNTIF('Lista Mestra'!$B$7:$B$59,"7. Checklist da visita"),0)) -> 0
A7: AUD-002 | B7: ANEXO BARAO DE MAMORE DA EM FRANCISCO DA SILVA NUNES | C7: {=IF(B7="","",IFERROR(INDEX('Cadastro Unidades'!$A$6:$A$222,MATCH(B7,'Cadastro Unidades'!$E$6:$E$222,0)),""))} -> DABEL | D7: Acompanhamento de pendências | J7: =IF(#REF!="","",COUNTIF('Auditoria Documental'!$A$7:$A$1000,#REF!)) -> #REF! | K7: =IF(#REF!="","",COUNTIFS('Auditoria Documental'!$A$7:$A$1000,#REF!,'Auditoria Documental'!$K$7:$K$1000,"<>Não avaliado",'Auditoria Documental'!$K$7:$K$1000,"<>")) -> #REF! | L7: =IF(#REF!="","",IFERROR(SUMIFS('Auditoria Documental'!$N$7:$N$1000,'Auditoria Documental'!$A$7:$A$1000,#REF!)/SUMIFS('Auditoria Documental'!$M$7:$M$1000,'Auditoria Documental'!$A$7:$A$1000,#REF!),0)) -> #REF! | M7: =IF(#REF!="","",COUNTIFS('Auditoria Documental'!$A$7:$A$1000,#REF!,'Auditoria Documental'!$J$7:$J$1000,3,'Auditoria Documental'!$K$7:$K$1000,"Não conforme")) -> #REF! | N7: =IF(#REF!="","",IFERROR(COUNTIFS('Auditoria Documental'!$A$7:$A$1000,#REF!,'Auditoria Documental'!$G$7:$G$1000,"7. Checklist da visita",'Auditoria Documental'!$K$7:$K$1000,"<>Não avaliado",'Auditoria Documental'!$K$7:$K$1000,"<>")/COUNTIF('Lista Mestra'!$B$7:$B$59,"7. Checklist da visita"),0)) -> #REF!
A8: AUD-003 | B8: ESCOLA MUNICIPAL PROF MIGUEL PERNAMBUCO FILHO | C8: {=IF(B8="","",IFERROR(INDEX('Cadastro Unidades'!$A$6:$A$222,MATCH(B8,'Cadastro Unidades'!$E$6:$E$222,0)),""))} -> DABEL | J8: =IF(A8="","",COUNTIF('Auditoria Documental'!$A$7:$A$1000,A8)) -> 0 | K8: =IF(A8="","",COUNTIFS('Auditoria Documental'!$A$7:$A$1000,A8,'Auditoria Documental'!$K$7:$K$1000,"<>Não avaliado",'Auditoria Documental'!$K$7:$K$1000,"<>")) -> 0 | L8: =IF(A8="","",IFERROR(SUMIFS('Auditoria Documental'!$N$7:$N$1000,'Auditoria Documental'!$A$7:$A$1000,A8)/SUMIFS('Auditoria Documental'!$M$7:$M$1000,'Auditoria Documental'!$A$7:$A$1000,A8),0)) -> 0 | M8: =IF(A8="","",COUNTIFS('Auditoria Documental'!$A$7:$A$1000,A8,'Auditoria Documental'!$J$7:$J$1000,3,'Auditoria Documental'!$K$7:$K$1000,"Não conforme")) -> 0 | N8: =IF(A8="","",IFERROR(COUNTIFS('Auditoria Documental'!$A$7:$A$1000,A8,'Auditoria Documental'!$G$7:$G$1000,"7. Checklist da visita",'Auditoria Documental'!$K$7:$K$1000,"<>Não avaliado",'Auditoria Documental'!$K$7:$K$1000,"<>")/COUNTIF('Lista Mestra'!$B$7:$B$59,"7. Checklist da visita"),0)) -> 0
A9: AUD-004 | B9: ANEXO CASA DA CRIANCA SANTA INES DA EM ALZIRA PERNAMBUCO | C9: {=IF(B9="","",IFERROR(INDEX('Cadastro Unidades'!$A$6:$A$222,MATCH(B9,'Cadastro Unidades'!$E$6:$E$222,0)),""))} -> DABEL | J9: =IF(A9="","",COUNTIF('Auditoria Documental'!$A$7:$A$1000,A9)) -> 0 | K9: =IF(A9="","",COUNTIFS('Auditoria Documental'!$A$7:$A$1000,A9,'Auditoria Documental'!$K$7:$K$1000,"<>Não avaliado",'Auditoria Documental'!$K$7:$K$1000,"<>")) -> 0 | L9: =IF(A9="","",IFERROR(SUMIFS('Auditoria Documental'!$N$7:$N$1000,'Auditoria Documental'!$A$7:$A$1000,A9)/SUMIFS('Auditoria Documental'!$M$7:$M$1000,'Auditoria Documental'!$A$7:$A$1000,A9),0)) -> 0 | M9: =IF(A9="","",COUNTIFS('Auditoria Documental'!$A$7:$A$1000,A9,'Auditoria Documental'!$J$7:$J$1000,3,'Auditoria Documental'!$K$7:$K$1000,"Não conforme")) -> 0 | N9: =IF(A9="","",IFERROR(COUNTIFS('Auditoria Documental'!$A$7:$A$1000,A9,'Auditoria Documental'!$G$7:$G$1000,"7. Checklist da visita",'Auditoria Documental'!$K$7:$K$1000,"<>Não avaliado",'Auditoria Documental'!$K$7:$K$1000,"<>")/COUNTIF('Lista Mestra'!$B$7:$B$59,"7. Checklist da visita"),0)) -> 0
A10: AUD-005 | B10: CENTRO EDUCACIONAL ARTE DE EDUCAR OSC ANEXO INSTITUTO ACELERA AMAZONIA | C10: {=IF(B10="","",IFERROR(INDEX('Cadastro Unidades'!$A$6:$A$222,MATCH(B10,'Cadastro Unidades'!$E$6:$E$222,0)),""))} -> DABEL | J10: =IF(A10="","",COUNTIF('Auditoria Documental'!$A$7:$A$1000,A10)) -> 0 | K10: =IF(A10="","",COUNTIFS('Auditoria Documental'!$A$7:$A$1000,A10,'Auditoria Documental'!$K$7:$K$1000,"<>Não avaliado",'Auditoria Documental'!$K$7:$K$1000,"<>")) -> 0 | L10: =IF(A10="","",IFERROR(SUMIFS('Auditoria Documental'!$N$7:$N$1000,'Auditoria Documental'!$A$7:$A$1000,A10)/SUMIFS('Auditoria Documental'!$M$7:$M$1000,'Auditoria Documental'!$A$7:$A$1000,A10),0)) -> 0 | M10: =IF(A10="","",COUNTIFS('Auditoria Documental'!$A$7:$A$1000,A10,'Auditoria Documental'!$J$7:$J$1000,3,'Auditoria Documental'!$K$7:$K$1000,"Não conforme")) -> 0 | N10: =IF(A10="","",IFERROR(COUNTIFS('Auditoria Documental'!$A$7:$A$1000,A10,'Auditoria Documental'!$G$7:$G$1000,"7. Checklist da visita",'Auditoria Documental'!$K$7:$K$1000,"<>Não avaliado",'Auditoria Documental'!$K$7:$K$1000,"<>")/COUNTIF('Lista Mestra'!$B$7:$B$59,"7. Checklist da visita"),0)) -> 0
A11: AUD-006 | B11: ESCOLA MUNICIPAL ALZIRA PERNAMBUCO | C11: {=IF(B11="","",IFERROR(INDEX('Cadastro Unidades'!$A$6:$A$222,MATCH(B11,'Cadastro Unidades'!$E$6:$E$222,0)),""))} -> DABEL | J11: =IF(A11="","",COUNTIF('Auditoria Documental'!$A$7:$A$1000,A11)) -> 0 | K11: =IF(A11="","",COUNTIFS('Auditoria Documental'!$A$7:$A$1000,A11,'Auditoria Documental'!$K$7:$K$1000,"<>Não avaliado",'Auditoria Documental'!$K$7:$K$1000,"<>")) -> 0 | L11: =IF(A11="","",IFERROR(SUMIFS('Auditoria Documental'!$N$7:$N$1000,'Auditoria Documental'!$A$7:$A$1000,A11)/SUMIFS('Auditoria Documental'!$M$7:$M$1000,'Auditoria Documental'!$A$7:$A$1000,A11),0)) -> 0 | M11: =IF(A11="","",COUNTIFS('Auditoria Documental'!$A$7:$A$1000,A11,'Auditoria Documental'!$J$7:$J$1000,3,'Auditoria Documental'!$K$7:$K$1000,"Não conforme")) -> 0 | N11: =IF(A11="","",IFERROR(COUNTIFS('Auditoria Documental'!$A$7:$A$1000,A11,'Auditoria Documental'!$G$7:$G$1000,"7. Checklist da visita",'Auditoria Documental'!$K$7:$K$1000,"<>Não avaliado",'Auditoria Documental'!$K$7:$K$1000,"<>")/COUNTIF('Lista Mestra'!$B$7:$B$59,"7. Checklist da visita"),0)) -> 0
A12: AUD-007 | B12: ESCOLA MUNICIPAL LIONS CLUBE DE BELEM | C12: {=IF(B12="","",IFERROR(INDEX('Cadastro Unidades'!$A$6:$A$222,MATCH(B12,'Cadastro Unidades'!$E$6:$E$222,0)),""))} -> DABEL | J12: =IF(A12="","",COUNTIF('Auditoria Documental'!$A$7:$A$1000,A12)) -> 0 | K12: =IF(A12="","",COUNTIFS('Auditoria Documental'!$A$7:$A$1000,A12,'Auditoria Documental'!$K$7:$K$1000,"<>Não avaliado",'Auditoria Documental'!$K$7:$K$1000,"<>")) -> 0 | L12: =IF(A12="","",IFERROR(SUMIFS('Auditoria Documental'!$N$7:$N$1000,'Auditoria Documental'!$A$7:$A$1000,A12)/SUMIFS('Auditoria Documental'!$M$7:$M$1000,'Auditoria Documental'!$A$7:$A$1000,A12),0)) -> 0 | M12: =IF(A12="","",COUNTIFS('Auditoria Documental'!$A$7:$A$1000,A12,'Auditoria Documental'!$J$7:$J$1000,3,'Auditoria Documental'!$K$7:$K$1000,"Não conforme")) -> 0 | N12: =IF(A12="","",IFERROR(COUNTIFS('Auditoria Documental'!$A$7:$A$1000,A12,'Auditoria Documental'!$G$7:$G$1000,"7. Checklist da visita",'Auditoria Documental'!$K$7:$K$1000,"<>Não avaliado",'Auditoria Documental'!$K$7:$K$1000,"<>")/COUNTIF('Lista Mestra'!$B$7:$B$59,"7. Checklist da visita"),0)) -> 0
A13: AUD-008 | B13: ESCOLA MUNICIPAL PROFESSORA LUCIA SOARES CASTRO | C13: {=IF(B13="","",IFERROR(INDEX('Cadastro Unidades'!$A$6:$A$222,MATCH(B13,'Cadastro Unidades'!$E$6:$E$222,0)),""))} -> DABEL | J13: =IF(A13="","",COUNTIF('Auditoria Documental'!$A$7:$A$1000,A13)) -> 0 | K13: =IF(A13="","",COUNTIFS('Auditoria Documental'!$A$7:$A$1000,A13,'Auditoria Documental'!$K$7:$K$1000,"<>Não avaliado",'Auditoria Documental'!$K$7:$K$1000,"<>")) -> 0 | L13: =IF(A13="","",IFERROR(SUMIFS('Auditoria Documental'!$N$7:$N$1000,'Auditoria Documental'!$A$7:$A$1000,A13)/SUMIFS('Auditoria Documental'!$M$7:$M$1000,'Auditoria Documental'!$A$7:$A$1000,A13),0)) -> 0 | M13: =IF(A13="","",COUNTIFS('Auditoria Documental'!$A$7:$A$1000,A13,'Auditoria Documental'!$J$7:$J$1000,3,'Auditoria Documental'!$K$7:$K$1000,"Não conforme")) -> 0 | N13: =IF(A13="","",IFERROR(COUNTIFS('Auditoria Documental'!$A$7:$A$1000,A13,'Auditoria Documental'!$G$7:$G$1000,"7. Checklist da visita",'Auditoria Documental'!$K$7:$K$1000,"<>Não avaliado",'Auditoria Documental'!$K$7:$K$1000,"<>")/COUNTIF('Lista Mestra'!$B$7:$B$59,"7. Checklist da visita"),0)) -> 0
A14: AUD-009 | B14: ESCOLA MUNICIPAL PROFESSORA RAIMUNDA LUCIA GUERREIRO | C14: {=IF(B14="","",IFERROR(INDEX('Cadastro Unidades'!$A$6:$A$222,MATCH(B14,'Cadastro Unidades'!$E$6:$E$222,0)),""))} -> DABEL | J14: =IF(A14="","",COUNTIF('Auditoria Documental'!$A$7:$A$1000,A14)) -> 0 | K14: =IF(A14="","",COUNTIFS('Auditoria Documental'!$A$7:$A$1000,A14,'Auditoria Documental'!$K$7:$K$1000,"<>Não avaliado",'Auditoria Documental'!$K$7:$K$1000,"<>")) -> 0 | L14: =IF(A14="","",IFERROR(SUMIFS('Auditoria Documental'!$N$7:$N$1000,'Auditoria Documental'!$A$7:$A$1000,A14)/SUMIFS('Auditoria Documental'!$M$7:$M$1000,'Auditoria Documental'!$A$7:$A$1000,A14),0)) -> 0 | M14: =IF(A14="","",COUNTIFS('Auditoria Documental'!$A$7:$A$1000,A14,'Auditoria Documental'!$J$7:$J$1000,3,'Auditoria Documental'!$K$7:$K$1000,"Não conforme")) -> 0 | N14: =IF(A14="","",IFERROR(COUNTIFS('Auditoria Documental'!$A$7:$A$1000,A14,'Auditoria Documental'!$G$7:$G$1000,"7. Checklist da visita",'Auditoria Documental'!$K$7:$K$1000,"<>Não avaliado",'Auditoria Documental'!$K$7:$K$1000,"<>")/COUNTIF('Lista Mestra'!$B$7:$B$59,"7. Checklist da visita"),0)) -> 0
A15: AUD-010 | B15: ESCOLA MUNICIPAL RUY DA SILVEIRA BRITTO | C15: {=IF(B15="","",IFERROR(INDEX('Cadastro Unidades'!$A$6:$A$222,MATCH(B15,'Cadastro Unidades'!$E$6:$E$222,0)),""))} -> DABEL | J15: =IF(A15="","",COUNTIF('Auditoria Documental'!$A$7:$A$1000,A15)) -> 0 | K15: =IF(A15="","",COUNTIFS('Auditoria Documental'!$A$7:$A$1000,A15,'Auditoria Documental'!$K$7:$K$1000,"<>Não avaliado",'Auditoria Documental'!$K$7:$K$1000,"<>")) -> 0 | L15: =IF(A15="","",IFERROR(SUMIFS('Auditoria Documental'!$N$7:$N$1000,'Auditoria Documental'!$A$7:$A$1000,A15)/SUMIFS('Auditoria Documental'!$M$7:$M$1000,'Auditoria Documental'!$A$7:$A$1000,A15),0)) -> 0 | M15: =IF(A15="","",COUNTIFS('Auditoria Documental'!$A$7:$A$1000,A15,'Auditoria Documental'!$J$7:$J$1000,3,'Auditoria Documental'!$K$7:$K$1000,"Não conforme")) -> 0 | N15: =IF(A15="","",IFERROR(COUNTIFS('Auditoria Documental'!$A$7:$A$1000,A15,'Auditoria Documental'!$G$7:$G$1000,"7. Checklist da visita",'Auditoria Documental'!$K$7:$K$1000,"<>Não avaliado",'Auditoria Documental'!$K$7:$K$1000,"<>")/COUNTIF('Lista Mestra'!$B$7:$B$59,"7. Checklist da visita"),0)) -> 0
A16: AUD-011 | B16: CENTRO DE REFERENCIA DE EDUCACAO INFANTIL PROF ORLANDO BITAR | C16: {=IF(B16="","",IFERROR(INDEX('Cadastro Unidades'!$A$6:$A$222,MATCH(B16,'Cadastro Unidades'!$E$6:$E$222,0)),""))} -> DABEL | J16: =IF(A16="","",COUNTIF('Auditoria Documental'!$A$7:$A$1000,A16)) -> 0 | K16: =IF(A16="","",COUNTIFS('Auditoria Documental'!$A$7:$A$1000,A16,'Auditoria Documental'!$K$7:$K$1000,"<>Não avaliado",'Auditoria Documental'!$K$7:$K$1000,"<>")) -> 0 | L16: =IF(A16="","",IFERROR(SUMIFS('Auditoria Documental'!$N$7:$N$1000,'Auditoria Documental'!$A$7:$A$1000,A16)/SUMIFS('Auditoria Documental'!$M$7:$M$1000,'Auditoria Documental'!$A$7:$A$1000,A16),0)) -> 0 | M16: =IF(A16="","",COUNTIFS('Auditoria Documental'!$A$7:$A$1000,A16,'Auditoria Documental'!$J$7:$J$1000,3,'Auditoria Documental'!$K$7:$K$1000,"Não conforme")) -> 0 | N16: =IF(A16="","",IFERROR(COUNTIFS('Auditoria Documental'!$A$7:$A$1000,A16,'Auditoria Documental'!$G$7:$G$1000,"7. Checklist da visita",'Auditoria Documental'!$K$7:$K$1000,"<>Não avaliado",'Auditoria Documental'!$K$7:$K$1000,"<>")/COUNTIF('Lista Mestra'!$B$7:$B$59,"7. Checklist da visita"),0)) -> 0
A17: AUD-012 | B17: INSTITUTO FELIPE SMALDONE BELEM | C17: {=IF(B17="","",IFERROR(INDEX('Cadastro Unidades'!$A$6:$A$222,MATCH(B17,'Cadastro Unidades'!$E$6:$E$222,0)),""))} -> DABEL | J17: =IF(A17="","",COUNTIF('Auditoria Documental'!$A$7:$A$1000,A17)) -> 0 | K17: =IF(A17="","",COUNTIFS('Auditoria Documental'!$A$7:$A$1000,A17,'Auditoria Documental'!$K$7:$K$1000,"<>Não avaliado",'Auditoria Documental'!$K$7:$K$1000,"<>")) -> 0 | L17: =IF(A17="","",IFERROR(SUMIFS('Auditoria Documental'!$N$7:$N$1000,'Auditoria Documental'!$A$7:$A$1000,A17)/SUMIFS('Auditoria Documental'!$M$7:$M$1000,'Auditoria Documental'!$A$7:$A$1000,A17),0)) -> 0 | M17: =IF(A17="","",COUNTIFS('Auditoria Documental'!$A$7:$A$1000,A17,'Auditoria Documental'!$J$7:$J$1000,3,'Auditoria Documental'!$K$7:$K$1000,"Não conforme")) -> 0 | N17: =IF(A17="","",IFERROR(COUNTIFS('Auditoria Documental'!$A$7:$A$1000,A17,'Auditoria Documental'!$G$7:$G$1000,"7. Checklist da visita",'Auditoria Documental'!$K$7:$K$1000,"<>Não avaliado",'Auditoria Documental'!$K$7:$K$1000,"<>")/COUNTIF('Lista Mestra'!$B$7:$B$59,"7. Checklist da visita"),0)) -> 0
A18: AUD-013 | B18: CRECHE CASA LAR CORDEIRINHO DE DEUS | C18: {=IF(B18="","",IFERROR(INDEX('Cadastro Unidades'!$A$6:$A$222,MATCH(B18,'Cadastro Unidades'!$E$6:$E$222,0)),""))} -> DABEL | J18: =IF(A18="","",COUNTIF('Auditoria Documental'!$A$7:$A$1000,A18)) -> 0 | K18: =IF(A18="","",COUNTIFS('Auditoria Documental'!$A$7:$A$1000,A18,'Auditoria Documental'!$K$7:$K$1000,"<>Não avaliado",'Auditoria Documental'!$K$7:$K$1000,"<>")) -> 0 | L18: =IF(A18="","",IFERROR(SUMIFS('Auditoria Documental'!$N$7:$N$1000,'Auditoria Documental'!$A$7:$A$1000,A18)/SUMIFS('Auditoria Documental'!$M$7:$M$1000,'Auditoria Documental'!$A$7:$A$1000,A18),0)) -> 0 | M18: =IF(A18="","",COUNTIFS('Auditoria Documental'!$A$7:$A$1000,A18,'Auditoria Documental'!$J$7:$J$1000,3,'Auditoria Documental'!$K$7:$K$1000,"Não conforme")) -> 0 | N18: =IF(A18="","",IFERROR(COUNTIFS('Auditoria Documental'!$A$7:$A$1000,A18,'Auditoria Documental'!$G$7:$G$1000,"7. Checklist da visita",'Auditoria Documental'!$K$7:$K$1000,"<>Não avaliado",'Auditoria Documental'!$K$7:$K$1000,"<>")/COUNTIF('Lista Mestra'!$B$7:$B$59,"7. Checklist da visita"),0)) -> 0
A19: AUD-014 | B19: ESCOLA MUNICIPAL BENVINDA DE FRANCA MESSIAS | C19: {=IF(B19="","",IFERROR(INDEX('Cadastro Unidades'!$A$6:$A$222,MATCH(B19,'Cadastro Unidades'!$E$6:$E$222,0)),""))} -> DABEL | J19: =IF(A19="","",COUNTIF('Auditoria Documental'!$A$7:$A$1000,A19)) -> 0 | K19: =IF(A19="","",COUNTIFS('Auditoria Documental'!$A$7:$A$1000,A19,'Auditoria Documental'!$K$7:$K$1000,"<>Não avaliado",'Auditoria Documental'!$K$7:$K$1000,"<>")) -> 0 | L19: =IF(A19="","",IFERROR(SUMIFS('Auditoria Documental'!$N$7:$N$1000,'Auditoria Documental'!$A$7:$A$1000,A19)/SUMIFS('Auditoria Documental'!$M$7:$M$1000,'Auditoria Documental'!$A$7:$A$1000,A19),0)) -> 0 | M19: =IF(A19="","",COUNTIFS('Auditoria Documental'!$A$7:$A$1000,A19,'Auditoria Documental'!$J$7:$J$1000,3,'Auditoria Documental'!$K$7:$K$1000,"Não conforme")) -> 0 | N19: =IF(A19="","",IFERROR(COUNTIFS('Auditoria Documental'!$A$7:$A$1000,A19,'Auditoria Documental'!$G$7:$G$1000,"7. Checklist da visita",'Auditoria Documental'!$K$7:$K$1000,"<>Não avaliado",'Auditoria Documental'!$K$7:$K$1000,"<>")/COUNTIF('Lista Mestra'!$B$7:$B$59,"7. Checklist da visita"),0)) -> 0
... A222: AUD-217 | B222: ESCOLA MUNICIPAL PERPETUO SOCORRO | C222: {=IF(B222="","",IFERROR(INDEX('Cadastro Unidades'!$A$6:$A$222,MATCH(B222,'Cadastro Unidades'!$E$6:$E$222,0)),""))} -> DASAC | J222: =IF(A222="","",COUNTIF('Auditoria Documental'!$A$7:$A$1000,A222)) -> 0 | K222: =IF(A222="","",COUNTIFS('Auditoria Documental'!$A$7:$A$1000,A222,'Auditoria Documental'!$K$7:$K$1000,"<>Não avaliado",'Auditoria Documental'!$K$7:$K$1000,"<>")) -> 0 | L222: =IF(A222="","",IFERROR(SUMIFS('Auditoria Documental'!$N$7:$N$1000,'Auditoria Documental'!$A$7:$A$1000,A222)/SUMIFS('Auditoria Documental'!$M$7:$M$1000,'Auditoria Documental'!$A$7:$A$1000,A222),0)) -> 0 | M222: =IF(A222="","",COUNTIFS('Auditoria Documental'!$A$7:$A$1000,A222,'Auditoria Documental'!$J$7:$J$1000,3,'Auditoria Documental'!$K$7:$K$1000,"Não conforme")) -> 0 | N222: =IF(A222="","",IFERROR(COUNTIFS('Auditoria Documental'!$A$7:$A$1000,A222,'Auditoria Documental'!$G$7:$G$1000,"7. Checklist da visita",'Auditoria Documental'!$K$7:$K$1000,"<>Não avaliado",'Auditoria Documental'!$K$7:$K$1000,"<>")/COUNTIF('Lista Mestra'!$B$7:$B$59,"7. Checklist da visita"),0)) -> 0

Sheet Auditoria Documental
A1: AUDITORIA DOCUMENTAL — CHECKLIST INTEGRAL
A2: Matriz de avaliação dos 53 registros do Checklist da CDE, com evidências, achados, pontuação e encaminhamento corretivo
A4: Preencha o Plano de Auditoria e classifique todos os itens do bloco AUD-0001. Para uma nova unidade, copie o bloco completo, altere o ID e ajuste o vínculo ao registro correspondente do plano.
A6: ID auditoria | B6: Data | C6: Unidade | D6: Distrito | E6: Auditor(a) | F6: Bairro | G6: Seção do Checklist | H6: Documento/item | I6: Evidência esperada | J6: Peso | K6: Situação | L6: Evidência/localização | M6: Peso aplicável | N6: Pontos | O6: Índice do item | P6: Achado/observação | Q6: Requer ação? | R6: Prazo | S6: Responsável | T6: Situação da ação
A7: AUD-0001 | B7: =IF('Plano de Auditoria'!$G$6<>"",'Plano de Auditoria'!$G$6,IF('Plano de Auditoria'!$F$6="","",'Plano de Auditoria'!$F$6)) | C7: =IF('Plano de Auditoria'!$B$6="","",'Plano de Auditoria'!$B$6) -> ESCOLA MUNICIPAL PROFESSORA MARIA AUXILIADORA MARTINS GONCALVES | D7: =IF('Plano de Auditoria'!$C$6="","",'Plano de Auditoria'!$C$6) -> DABEL | E7: =IF('Plano de Auditoria'!$H$6="","",'Plano de Auditoria'!$H$6) | F7: MARCO | G7: 1. Documentos institucionais | H7: Ato de criação da escola | I7: Ato integral, legível e disponível para conferência. | J7: 3 | K7: Não avaliado | M7: =IF(OR(K7="Não se aplica",K7="",J7=0),0,J7) -> 3 | N7: =IF(K7="Conforme",M7,IF(K7="Parcialmente conforme",M7*0.5,0)) -> 0 | O7: =IF(M7=0,"",N7/M7) -> 0 | Q7: Não
A8: AUD-0001 | B8: =IF('Plano de Auditoria'!$G$6<>"",'Plano de Auditoria'!$G$6,IF('Plano de Auditoria'!$F$6="","",'Plano de Auditoria'!$F$6)) | C8: =IF('Plano de Auditoria'!$B$6="","",'Plano de Auditoria'!$B$6) -> ESCOLA MUNICIPAL PROFESSORA MARIA AUXILIADORA MARTINS GONCALVES | D8: =IF('Plano de Auditoria'!$C$6="","",'Plano de Auditoria'!$C$6) -> DABEL | E8: =IF('Plano de Auditoria'!$H$6="","",'Plano de Auditoria'!$H$6) | F8: MARCO | G8: 1. Documentos institucionais | H8: Recibo do Censo Escolar (Autorização) | I8: Recibo do Censo Escolar e comprovantes correspondentes. | J8: 2 | K8: Não avaliado | M8: =IF(OR(K8="Não se aplica",K8="",J8=0),0,J8) -> 2 | N8: =IF(K8="Conforme",M8,IF(K8="Parcialmente conforme",M8*0.5,0)) -> 0 | O8: =IF(M8=0,"",N8/M8) -> 0 | Q8: Não
A9: AUD-0001 | B9: =IF('Plano de Auditoria'!$G$6<>"",'Plano de Auditoria'!$G$6,IF('Plano de Auditoria'!$F$6="","",'Plano de Auditoria'!$F$6)) | C9: =IF('Plano de Auditoria'!$B$6="","",'Plano de Auditoria'!$B$6) -> ESCOLA MUNICIPAL PROFESSORA MARIA AUXILIADORA MARTINS GONCALVES | D9: =IF('Plano de Auditoria'!$C$6="","",'Plano de Auditoria'!$C$6) -> DABEL | E9: =IF('Plano de Auditoria'!$H$6="","",'Plano de Auditoria'!$H$6) | F9: MARCO | G9: 1. Documentos institucionais | H9: Ato de autorização, credenciamento ou reconhecimento | I9: Ato completo, vigente e compatível com as etapas/modalidades ofertadas. | J9: 3 | K9: Não avaliado | M9: =IF(OR(K9="Não se aplica",K9="",J9=0),0,J9) -> 3 | N9: =IF(K9="Conforme",M9,IF(K9="Parcialmente conforme",M9*0.5,0)) -> 0 | O9: =IF(M9=0,"",N9/M9) -> 0 | Q9: Não
A10: AUD-0001 | B10: =IF('Plano de Auditoria'!$G$6<>"",'Plano de Auditoria'!$G$6,IF('Plano de Auditoria'!$F$6="","",'Plano de Auditoria'!$F$6)) | C10: =IF('Plano de Auditoria'!$B$6="","",'Plano de Auditoria'!$B$6) -> ESCOLA MUNICIPAL PROFESSORA MARIA AUXILIADORA MARTINS GONCALVES | D10: =IF('Plano de Auditoria'!$C$6="","",'Plano de Auditoria'!$C$6) -> DABEL | E10: =IF('Plano de Auditoria'!$H$6="","",'Plano de Auditoria'!$H$6) | F10: MARCO | G10: 1. Documentos institucionais | H10: Regimento Escolar atualizado | I10: Versão atualizada, aprovada, datada e disponível. | J10: 2 | K10: Não avaliado | M10: =IF(OR(K10="Não se aplica",K10="",J10=0),0,J10) -> 2 | N10: =IF(K10="Conforme",M10,IF(K10="Parcialmente conforme",M10*0.5,0)) -> 0 | O10: =IF(M10=0,"",N10/M10) -> 0 | Q10: Não
A11: AUD-0001 | B11: =IF('Plano de Auditoria'!$G$6<>"",'Plano de Auditoria'!$G$6,IF('Plano de Auditoria'!$F$6="","",'Plano de Auditoria'!$F$6)) | C11: =IF('Plano de Auditoria'!$B$6="","",'Plano de Auditoria'!$B$6) -> ESCOLA MUNICIPAL PROFESSORA MARIA AUXILIADORA MARTINS GONCALVES | D11: =IF('Plano de Auditoria'!$C$6="","",'Plano de Auditoria'!$C$6) -> DABEL | E11: =IF('Plano de Auditoria'!$H$6="","",'Plano de Auditoria'!$H$6) | F11: MARCO | G11: 1. Documentos institucionais | H11: Projeto Político-Pedagógico (PPP) | I11: PPP atualizado, aprovado e disponível. | J11: 2 | K11: Não avaliado | M11: =IF(OR(K11="Não se aplica",K11="",J11=0),0,J11) -> 2 | N11: =IF(K11="Conforme",M11,IF(K11="Parcialmente conforme",M11*0.5,0)) -> 0 | O11: =IF(M11=0,"",N11/M11) -> 0 | Q11: Não
A12: AUD-0001 | B12: =IF('Plano de Auditoria'!$G$6<>"",'Plano de Auditoria'!$G$6,IF('Plano de Auditoria'!$F$6="","",'Plano de Auditoria'!$F$6)) | C12: =IF('Plano de Auditoria'!$B$6="","",'Plano de Auditoria'!$B$6) -> ESCOLA MUNICIPAL PROFESSORA MARIA AUXILIADORA MARTINS GONCALVES | D12: =IF('Plano de Auditoria'!$C$6="","",'Plano de Auditoria'!$C$6) -> DABEL | E12: =IF('Plano de Auditoria'!$H$6="","",'Plano de Auditoria'!$H$6) | F12: MARCO | G12: 1. Documentos institucionais | H12: Calendário Escolar vigente | I12: Calendário acessível no SIGA: Administração > Calendário Escolar > Acessar Calendário. | J12: 2 | K12: Não avaliado | M12: =IF(OR(K12="Não se aplica",K12="",J12=0),0,J12) -> 2 | N12: =IF(K12="Conforme",M12,IF(K12="Parcialmente conforme",M12*0.5,0)) -> 0 | O12: =IF(M12=0,"",N12/M12) -> 0 | Q12: Não
A13: AUD-0001 | B13: =IF('Plano de Auditoria'!$G$6<>"",'Plano de Auditoria'!$G$6,IF('Plano de Auditoria'!$F$6="","",'Plano de Auditoria'!$F$6)) | C13: =IF('Plano de Auditoria'!$B$6="","",'Plano de Auditoria'!$B$6) -> ESCOLA MUNICIPAL PROFESSORA MARIA AUXILIADORA MARTINS GONCALVES | D13: =IF('Plano de Auditoria'!$C$6="","",'Plano de Auditoria'!$C$6) -> DABEL | E13: =IF('Plano de Auditoria'!$H$6="","",'Plano de Auditoria'!$H$6) | F13: MARCO | G13: 1. Documentos institucionais | H13: Matriz curricular, inclusive cursos técnicos | I13: Matriz vigente por etapa/modalidade, com componentes e cargas horárias. | J13: 3 | K13: Não avaliado | M13: =IF(OR(K13="Não se aplica",K13="",J13=0),0,J13) -> 3 | N13: =IF(K13="Conforme",M13,IF(K13="Parcialmente conforme",M13*0.5,0)) -> 0 | O13: =IF(M13=0,"",N13/M13) -> 0 | Q13: Não
A14: AUD-0001 | B14: =IF('Plano de Auditoria'!$G$6<>"",'Plano de Auditoria'!$G$6,IF('Plano de Auditoria'!$F$6="","",'Plano de Auditoria'!$F$6)) | C14: =IF('Plano de Auditoria'!$B$6="","",'Plano de Auditoria'!$B$6) -> ESCOLA MUNICIPAL PROFESSORA MARIA AUXILIADORA MARTINS GONCALVES | D14: =IF('Plano de Auditoria'!$C$6="","",'Plano de Auditoria'!$C$6) -> DABEL | E14: =IF('Plano de Auditoria'!$H$6="","",'Plano de Auditoria'!$H$6) | F14: MARCO | G14: 2. Secretaria escolar | H14: Livro de Matrícula | I14: Livro completo, atualizado e com termos de abertura e encerramento. | J14: 3 | K14: Não avaliado | M14: =IF(OR(K14="Não se aplica",K14="",J14=0),0,J14) -> 3 | N14: =IF(K14="Conforme",M14,IF(K14="Parcialmente conforme",M14*0.5,0)) -> 0 | O14: =IF(M14=0,"",N14/M14) -> 0 | Q14: Não
A15: AUD-0001 | B15: =IF('Plano de Auditoria'!$G$6<>"",'Plano de Auditoria'!$G$6,IF('Plano de Auditoria'!$F$6="","",'Plano de Auditoria'!$F$6)) | C15: =IF('Plano de Auditoria'!$B$6="","",'Plano de Auditoria'!$B$6) -> ESCOLA MUNICIPAL PROFESSORA MARIA AUXILIADORA MARTINS GONCALVES | D15: =IF('Plano de Auditoria'!$C$6="","",'Plano de Auditoria'!$C$6) -> DABEL | E15: =IF('Plano de Auditoria'!$H$6="","",'Plano de Auditoria'!$H$6) | F15: MARCO | G15: 2. Secretaria escolar | H15: Livro de Atas — resultados finais, Conselho de Classe, reuniões e outros | I15: Livros completos, sequenciais, datados e assinados. | J15: 3 | K15: Não avaliado | M15: =IF(OR(K15="Não se aplica",K15="",J15=0),0,J15) -> 3 | N15: =IF(K15="Conforme",M15,IF(K15="Parcialmente conforme",M15*0.5,0)) -> 0 | O15: =IF(M15=0,"",N15/M15) -> 0 | Q15: Não
A16: AUD-0001 | B16: =IF('Plano de Auditoria'!$G$6<>"",'Plano de Auditoria'!$G$6,IF('Plano de Auditoria'!$F$6="","",'Plano de Auditoria'!$F$6)) | C16: =IF('Plano de Auditoria'!$B$6="","",'Plano de Auditoria'!$B$6) -> ESCOLA MUNICIPAL PROFESSORA MARIA AUXILIADORA MARTINS GONCALVES | D16: =IF('Plano de Auditoria'!$C$6="","",'Plano de Auditoria'!$C$6) -> DABEL | E16: =IF('Plano de Auditoria'!$H$6="","",'Plano de Auditoria'!$H$6) | F16: MARCO | G16: 2. Secretaria escolar | H16: Livro de Registro de Diplomas e Certificados, quando aplicável | I16: Registro sequencial, íntegro e rastreável dos documentos expedidos. | J16: 3 | K16: Não avaliado | M16: =IF(OR(K16="Não se aplica",K16="",J16=0),0,J16) -> 3 | N16: =IF(K16="Conforme",M16,IF(K16="Parcialmente conforme",M16*0.5,0)) -> 0 | O16: =IF(M16=0,"",N16/M16) -> 0 | Q16: Não
A17: AUD-0001 | B17: =IF('Plano de Auditoria'!$G$6<>"",'Plano de Auditoria'!$G$6,IF('Plano de Auditoria'!$F$6="","",'Plano de Auditoria'!$F$6)) | C17: =IF('Plano de Auditoria'!$B$6="","",'Plano de Auditoria'!$B$6) -> ESCOLA MUNICIPAL PROFESSORA MARIA AUXILIADORA MARTINS GONCALVES | D17: =IF('Plano de Auditoria'!$C$6="","",'Plano de Auditoria'!$C$6) -> DABEL | E17: =IF('Plano de Auditoria'!$H$6="","",'Plano de Auditoria'!$H$6) | F17: MARCO | G17: 2. Secretaria escolar | H17: Protocolos de entrada e saída de documentos | I17: Registros cronológicos de recebimento, tramitação e entrega. | J17: 2 | K17: Não avaliado | M17: =IF(OR(K17="Não se aplica",K17="",J17=0),0,J17) -> 2 | N17: =IF(K17="Conforme",M17,IF(K17="Parcialmente conforme",M17*0.5,0)) -> 0 | O17: =IF(M17=0,"",N17/M17) -> 0 | Q17: Não
A18: AUD-0001 | B18: =IF('Plano de Auditoria'!$G$6<>"",'Plano de Auditoria'!$G$6,IF('Plano de Auditoria'!$F$6="","",'Plano de Auditoria'!$F$6)) | C18: =IF('Plano de Auditoria'!$B$6="","",'Plano de Auditoria'!$B$6) -> ESCOLA MUNICIPAL PROFESSORA MARIA AUXILIADORA MARTINS GONCALVES | D18: =IF('Plano de Auditoria'!$C$6="","",'Plano de Auditoria'!$C$6) -> DABEL | E18: =IF('Plano de Auditoria'!$H$6="","",'Plano de Auditoria'!$H$6) | F18: MARCO | G18: 2. Secretaria escolar | H18: Arquivo ativo e arquivo permanente organizados | I18: Pastas classificadas, preservadas, localizáveis e com acesso controlado. | J18: 3 | K18: Não avaliado | M18: =IF(OR(K18="Não se aplica",K18="",J18=0),0,J18) -> 3 | N18: =IF(K18="Conforme",M18,IF(K18="Parcialmente conforme",M18*0.5,0)) -> 0 | O18: =IF(M18=0,"",N18/M18) -> 0 | Q18: Não
... A59: AUD-0001 | B59: =IF('Plano de Auditoria'!$G$6<>"",'Plano de Auditoria'!$G$6,IF('Plano de Auditoria'!$F$6="","",'Plano de Auditoria'!$F$6)) | C59: =IF('Plano de Auditoria'!$B$6="","",'Plano de Auditoria'!$B$6) -> ESCOLA MUNICIPAL PROFESSORA MARIA AUXILIADORA MARTINS GONCALVES | D59: =IF('Plano de Auditoria'!$C$6="","",'Plano de Auditoria'!$C$6) -> DABEL | E59: =IF('Plano de Auditoria'!$H$6="","",'Plano de Auditoria'!$H$6) | F59: MARCO | G59: 7. Checklist da visita | H59: Dados do Censo Escolar conferidos | I59: Síntese de conferência da visita. | J59: 0 | K59: Não avaliado | M59: =IF(OR(K59="Não se aplica",K59="",J59=0),0,J59) -> 0 | N59: =IF(K59="Conforme",M59,IF(K59="Parcialmente conforme",M59*0.5,0)) -> 0 | O59: =IF(M59=0,"",N59/M59) | Q59: Não
B60: =IF('Plano de Auditoria'!$G$6<>"",'Plano de Auditoria'!$G$6,IF('Plano de Auditoria'!$F$6="","",'Plano de Auditoria'!$F$6)) | E60: =IF('Plano de Auditoria'!$H$6="","",'Plano de Auditoria'!$H$6) | M60: =IF(OR(K60="Não se aplica",K60="",J60=0),0,J60) -> 0 | N60: =IF(K60="Conforme",M60,IF(K60="Parcialmente conforme",M60*0.5,0)) -> 0 | O60: =IF(M60=0,"",N60/M60)

Sheet Checklist da Visita
A1: CHECKLIST PARA A VISITA TÉCNICA
A2: Síntese operacional dos 12 itens finais do Checklist da Coordenadoria de Documentação Escolar
A4: Auditoria | C4: ='Plano de Auditoria'!A7 -> AUD-002 | E4: Data da visita | G4: =IF('Plano de Auditoria'!G6<>"",'Plano de Auditoria'!G6,IF('Plano de Auditoria'!F6="","",'Plano de Auditoria'!F6))
A5: Unidade | G5: Distrito | H5: =IF('Plano de Auditoria'!C6="","",'Plano de Auditoria'!C6) -> DABEL
A6: Auditor(a)/equipe | C6: =IF('Plano de Auditoria'!H6="","",'Plano de Auditoria'!H6) | G6: Conclusão | H6: ='Plano de Auditoria'!N6 -> 0
A8: Nº | B8: Item do Checklist para a visita | C8: Situação | D8: Evidência/localização | E8: Achado/observação | F8: Requer ação? | G8: Responsável | H8: Prazo
A9: 1 | B9: Regimento Escolar atualizado | C9: ='Auditoria Documental'!K48 -> Não avaliado | D9: =IF('Auditoria Documental'!L48="","",'Auditoria Documental'!L48) | E9: =IF('Auditoria Documental'!P48="","",'Auditoria Documental'!P48) | F9: ='Auditoria Documental'!Q48 -> Não | G9: =IF('Auditoria Documental'!S48="","",'Auditoria Documental'!S48) | H9: =IF('Auditoria Documental'!R48="","",'Auditoria Documental'!R48)
A10: 2 | B10: PPP atualizado | C10: ='Auditoria Documental'!K49 -> Não avaliado | D10: =IF('Auditoria Documental'!L49="","",'Auditoria Documental'!L49) | E10: =IF('Auditoria Documental'!P49="","",'Auditoria Documental'!P49) | F10: ='Auditoria Documental'!Q49 -> Não | G10: =IF('Auditoria Documental'!S49="","",'Auditoria Documental'!S49) | H10: =IF('Auditoria Documental'!R49="","",'Auditoria Documental'!R49)
A11: 3 | B11: Calendário Escolar aprovado | C11: ='Auditoria Documental'!K50 -> Não avaliado | D11: =IF('Auditoria Documental'!L50="","",'Auditoria Documental'!L50) | E11: =IF('Auditoria Documental'!P50="","",'Auditoria Documental'!P50) | F11: ='Auditoria Documental'!Q50 -> Não | G11: =IF('Auditoria Documental'!S50="","",'Auditoria Documental'!S50) | H11: =IF('Auditoria Documental'!R50="","",'Auditoria Documental'!R50)
A12: 4 | B12: Livros oficiais completos e assinados | C12: ='Auditoria Documental'!K51 -> Não avaliado | D12: =IF('Auditoria Documental'!L51="","",'Auditoria Documental'!L51) | E12: =IF('Auditoria Documental'!P51="","",'Auditoria Documental'!P51) | F12: ='Auditoria Documental'!Q51 -> Não | G12: =IF('Auditoria Documental'!S51="","",'Auditoria Documental'!S51) | H12: =IF('Auditoria Documental'!R51="","",'Auditoria Documental'!R51)
A13: 5 | B13: Diários de Classe atualizados | C13: ='Auditoria Documental'!K52 -> Não avaliado | D13: =IF('Auditoria Documental'!L52="","",'Auditoria Documental'!L52) | E13: =IF('Auditoria Documental'!P52="","",'Auditoria Documental'!P52) | F13: ='Auditoria Documental'!Q52 -> Não | G13: =IF('Auditoria Documental'!S52="","",'Auditoria Documental'!S52) | H13: =IF('Auditoria Documental'!R52="","",'Auditoria Documental'!R52)
A14: 6 | B14: Atas de resultados finais e conselhos | C14: ='Auditoria Documental'!K53 -> Não avaliado | D14: =IF('Auditoria Documental'!L53="","",'Auditoria Documental'!L53) | E14: =IF('Auditoria Documental'!P53="","",'Auditoria Documental'!P53) | F14: ='Auditoria Documental'!Q53 -> Não | G14: =IF('Auditoria Documental'!S53="","",'Auditoria Documental'!S53) | H14: =IF('Auditoria Documental'!R53="","",'Auditoria Documental'!R53)
A15: 7 | B15: Históricos escolares organizados | C15: ='Auditoria Documental'!K54 -> Não avaliado | D15: =IF('Auditoria Documental'!L54="","",'Auditoria Documental'!L54) | E15: =IF('Auditoria Documental'!P54="","",'Auditoria Documental'!P54) | F15: ='Auditoria Documental'!Q54 -> Não | G15: =IF('Auditoria Documental'!S54="","",'Auditoria Documental'!S54) | H15: =IF('Auditoria Documental'!R54="","",'Auditoria Documental'!R54)
A16: 8 | B16: Fichas de matrícula completas | C16: ='Auditoria Documental'!K55 -> Não avaliado | D16: =IF('Auditoria Documental'!L55="","",'Auditoria Documental'!L55) | E16: =IF('Auditoria Documental'!P55="","",'Auditoria Documental'!P55) | F16: ='Auditoria Documental'!Q55 -> Não | G16: =IF('Auditoria Documental'!S55="","",'Auditoria Documental'!S55) | H16: =IF('Auditoria Documental'!R55="","",'Auditoria Documental'!R55)
A17: 9 | B17: Arquivo ativo e permanente organizado | C17: ='Auditoria Documental'!K56 -> Não avaliado | D17: =IF('Auditoria Documental'!L56="","",'Auditoria Documental'!L56) | E17: =IF('Auditoria Documental'!P56="","",'Auditoria Documental'!P56) | F17: ='Auditoria Documental'!Q56 -> Não | G17: =IF('Auditoria Documental'!S56="","",'Auditoria Documental'!S56) | H17: =IF('Auditoria Documental'!R56="","",'Auditoria Documental'!R56)
A18: 10 | B18: Relação de alunos e servidores atualizada | C18: ='Auditoria Documental'!K57 -> Não avaliado | D18: =IF('Auditoria Documental'!L57="","",'Auditoria Documental'!L57) | E18: =IF('Auditoria Documental'!P57="","",'Auditoria Documental'!P57) | F18: ='Auditoria Documental'!Q57 -> Não | G18: =IF('Auditoria Documental'!S57="","",'Auditoria Documental'!S57) | H18: =IF('Auditoria Documental'!R57="","",'Auditoria Documental'!R57)
A19: 11 | B19: Documentação legal da escola disponível | C19: ='Auditoria Documental'!K58 -> Não avaliado | D19: =IF('Auditoria Documental'!L58="","",'Auditoria Documental'!L58) | E19: =IF('Auditoria Documental'!P58="","",'Auditoria Documental'!P58) | F19: ='Auditoria Documental'!Q58 -> Não | G19: =IF('Auditoria Documental'!S58="","",'Auditoria Documental'!S58) | H19: =IF('Auditoria Documental'!R58="","",'Auditoria Documental'!R58)
A20: 12 | B20: Dados do Censo Escolar conferidos | C20: ='Auditoria Documental'!K59 -> Não avaliado | D20: =IF('Auditoria Documental'!L59="","",'Auditoria Documental'!L59) | E20: =IF('Auditoria Documental'!P59="","",'Auditoria Documental'!P59) | F20: ='Auditoria Documental'!Q59 -> Não | G20: =IF('Auditoria Documental'!S59="","",'Auditoria Documental'!S59) | H20: =IF('Auditoria Documental'!R59="","",'Auditoria Documental'!R59)
A22: Esta aba é uma síntese automática. Para alterar situação, evidência, achado, responsável ou prazo, utilize as linhas VIS-01 a VIS-12 da aba Auditoria Documental.

Sheet Plano de Ação
A1: PLANO DE AÇÃO CORRETIVA
A2: Tratamento, acompanhamento e validação das não conformidades identificadas
A4: Registre uma ação para cada pendência relevante, informando prioridade, responsável, prazo e evidência de conclusão. A baixa depende de validação da CDE.
A6: ID ação | B6: ID auditoria | C6: Unidade | D6: Código do item | E6: Achado | F6: Ação corretiva | G6: Prioridade | H6: Responsável | I6: Data de abertura | J6: Prazo | K6: Dias restantes | L6: Situação | M6: Evidência de conclusão | N6: Data de conclusão | O6: Validação CDE
K7: =IF(J7="","",J7-TODAY())
K8: =IF(J8="","",J8-TODAY())
K9: =IF(J9="","",J9-TODAY())
K10: =IF(J10="","",J10-TODAY())
K11: =IF(J11="","",J11-TODAY())
K12: =IF(J12="","",J12-TODAY())
K13: =IF(J13="","",J13-TODAY())
K14: =IF(J14="","",J14-TODAY())
K15: =IF(J15="","",J15-TODAY())
K16: =IF(J16="","",J16-TODAY())
K17: =IF(J17="","",J17-TODAY())
K18: =IF(J18="","",J18-TODAY())
... K506: =IF(J506="","",J506-TODAY())

Sheet Dashboard
A1: PAINEL DE CONTROLE DA DOCUMENTAÇÃO ESCOLAR
A2: Coordenadoria de Documentação Escolar — visão executiva das unidades, auditorias, conformidade documental e ações corretivas
T3: Situação | U3: Quantidade
T4: Conforme | U4: =COUNTIF('Auditoria Documental'!$K$7:$K$1000,T4) -> 0
A5: Unidades cadastradas | D5: Itens do Checklist | G5: Auditorias registradas | J5: Itens avaliados | M5: Não conformes | P5: Índice global | T5: Parcialmente conforme | U5: =COUNTIF('Auditoria Documental'!$K$7:$K$1000,T5) -> 0
A6: =COUNTA('Cadastro Unidades'!$E$6:$E$222) -> 217 | D6: =COUNTA('Lista Mestra'!$A$7:$A$59) -> 53 | G6: =COUNTA('Plano de Auditoria'!$A$6:$A$223) -> 217 | J6: =COUNTIFS('Auditoria Documental'!$K$7:$K$1000,"<>Não avaliado",'Auditoria Documental'!$K$7:$K$1000,"<>") -> 0 | M6: =COUNTIF('Auditoria Documental'!$K$7:$K$1000,"Não conforme") -> 0 | P6: =IFERROR(SUM('Auditoria Documental'!$N$7:$N$1000)/SUM('Auditoria Documental'!$M$7:$M$1000),0) -> 0 | T6: Não conforme | U6: =COUNTIF('Auditoria Documental'!$K$7:$K$1000,T6) -> 0
T7: Não se aplica | U7: =COUNTIF('Auditoria Documental'!$K$7:$K$1000,T7) -> 0
T8: Não avaliado | U8: =COUNTIF('Auditoria Documental'!$K$7:$K$1000,T8) -> 53
A9: Base territorial e de endereços | D9: 100% dos registros do documento | G9: Planejamento por unidade | J9: Verificações concluídas | M9: Providências necessárias | P9: Conformidade ponderada
T11: Seção | U11: Itens
T12: Institucionais | U12: =COUNTIF('Lista Mestra'!$B$7:$B$59,"1. Documentos institucionais") -> 7
T13: Secretaria escolar | U13: =COUNTIF('Lista Mestra'!$B$7:$B$59,"2. Secretaria escolar") -> 8
T14: Estudantes | U14: =COUNTIF('Lista Mestra'!$B$7:$B$59,"3. Documentação dos estudantes") -> 9
T15: Servidores | U15: =COUNTIF('Lista Mestra'!$B$7:$B$59,"4. Documentação dos servidores") -> 5
T16: Administrativos | U16: =COUNTIF('Lista Mestra'!$B$7:$B$59,"5. Documentos administrativos") -> 5
T17: Verificações CDE | U17: =COUNTIF('Lista Mestra'!$B$7:$B$59,"6. Itens verificados pela CDE") -> 7
T18: Checklist da visita | U18: =COUNTIF('Lista Mestra'!$B$7:$B$59,"7. Checklist da visita") -> 12
T21: Distrito | U21: Municipal | V21: OSC/Conveniada
T22: DABEL | U22: =COUNTIFS('Cadastro Unidades'!$A$6:$A$222,T22,'Cadastro Unidades'!$C$6:$C$222,"MUNICIPAL") -> 14 | V22: =COUNTIFS('Cadastro Unidades'!$A$6:$A$222,T22,'Cadastro Unidades'!$C$6:$C$222,"OSC/CONVENIADA") -> 3
T23: DABEN | U23: =COUNTIFS('Cadastro Unidades'!$A$6:$A$222,T23,'Cadastro Unidades'!$C$6:$C$222,"MUNICIPAL") -> 35 | V23: =COUNTIFS('Cadastro Unidades'!$A$6:$A$222,T23,'Cadastro Unidades'!$C$6:$C$222,"OSC/CONVENIADA") -> 10
T24: DAENT | U24: =COUNTIFS('Cadastro Unidades'!$A$6:$A$222,T24,'Cadastro Unidades'!$C$6:$C$222,"MUNICIPAL") -> 19 | V24: =COUNTIFS('Cadastro Unidades'!$A$6:$A$222,T24,'Cadastro Unidades'!$C$6:$C$222,"OSC/CONVENIADA") -> 3
T25: DAGUA | U25: =COUNTIFS('Cadastro Unidades'!$A$6:$A$222,T25,'Cadastro Unidades'!$C$6:$C$222,"MUNICIPAL") -> 31 | V25: =COUNTIFS('Cadastro Unidades'!$A$6:$A$222,T25,'Cadastro Unidades'!$C$6:$C$222,"OSC/CONVENIADA") -> 8
N26: QUALIDADE DO CADASTRO TERRITORIAL | T26: DAICO | U26: =COUNTIFS('Cadastro Unidades'!$A$6:$A$222,T26,'Cadastro Unidades'!$C$6:$C$222,"MUNICIPAL") -> 24 | V26: =COUNTIFS('Cadastro Unidades'!$A$6:$A$222,T26,'Cadastro Unidades'!$C$6:$C$222,"OSC/CONVENIADA") -> 9
N27: Indicador | P27: Registros | Q27: Cobertura | T27: DAMOS | U27: =COUNTIFS('Cadastro Unidades'!$A$6:$A$222,T27,'Cadastro Unidades'!$C$6:$C$222,"MUNICIPAL") -> 15 | V27: =COUNTIFS('Cadastro Unidades'!$A$6:$A$222,T27,'Cadastro Unidades'!$C$6:$C$222,"OSC/CONVENIADA") -> 4
N28: Logradouro informado | P28: =COUNTA('Cadastro Unidades'!$L$6:$L$222) -> 217 | Q28: =IFERROR(P28/COUNTA('Cadastro Unidades'!$E$6:$E$222),0) -> 1 | T28: DAOUT | U28: =COUNTIFS('Cadastro Unidades'!$A$6:$A$222,T28,'Cadastro Unidades'!$C$6:$C$222,"MUNICIPAL") -> 18 | V28: =COUNTIFS('Cadastro Unidades'!$A$6:$A$222,T28,'Cadastro Unidades'!$C$6:$C$222,"OSC/CONVENIADA") -> 2
N29: CEP informado | P29: =COUNTA('Cadastro Unidades'!$O$6:$O$222) -> 217 | Q29: =IFERROR(P29/COUNTA('Cadastro Unidades'!$E$6:$E$222),0) -> 1 | T29: DASAC | U29: =COUNTIFS('Cadastro Unidades'!$A$6:$A$222,T29,'Cadastro Unidades'!$C$6:$C$222,"MUNICIPAL") -> 19 | V29: =COUNTIFS('Cadastro Unidades'!$A$6:$A$222,T29,'Cadastro Unidades'!$C$6:$C$222,"OSC/CONVENIADA") -> 3
N30: Telefone informado | P30: =COUNTA('Cadastro Unidades'!$P$6:$P$222) -> 21 | Q30: =IFERROR(P30/COUNTA('Cadastro Unidades'!$E$6:$E$222),0) -> 0.096774194
N31: E-mail informado | P31: =COUNTA('Cadastro Unidades'!$Q$6:$Q$222) -> 165 | Q31: =IFERROR(P31/COUNTA('Cadastro Unidades'!$E$6:$E$222),0) -> 0.76036866
N32: Situação ativa | P32: =COUNTIF('Cadastro Unidades'!$F$6:$F$222,"ATIVA") -> 217 | Q32: =IFERROR(P32/COUNTA('Cadastro Unidades'!$E$6:$E$222),0) -> 1
N34: LEGENDA DE GESTÃO
N35: Conforme | R35: Atende integralmente
N36: Parcialmente conforme | R36: Exige complementação
N37: Não conforme | R37: Exige ação corretiva
N38: Não se aplica | R38: Justificar exclusão
N39: Não avaliado | R39: Verificação pendente
A41: O índice global considera apenas os 41 itens técnicos. Os 12 itens do Checklist da Visita permanecem integralmente registrados como síntese de conferência, com peso zero para evitar dupla contagem.

Sheet Relatórios
A1: RELATÓRIOS GERENCIAIS
A2: Consolidação automática da conformidade documental, das auditorias e da distribuição territorial das unidades
A4: A matriz apresenta todos os itens do Checklist. O índice ponderado é calculado apenas quando a seção possui peso técnico superior a zero.
A6: Seção do Checklist | B6: Conforme | C6: Parcialmente conforme | D6: Não conforme | E6: Não se aplica | F6: Não avaliado | G6: Itens registrados | H6: Índice ponderado
A7: 1. Documentos institucionais | B7: =COUNTIFS('Auditoria Documental'!$G$7:$G$1000,$A7,'Auditoria Documental'!$K$7:$K$1000,B$6) -> 0 | C7: =COUNTIFS('Auditoria Documental'!$G$7:$G$1000,$A7,'Auditoria Documental'!$K$7:$K$1000,C$6) -> 0 | D7: =COUNTIFS('Auditoria Documental'!$G$7:$G$1000,$A7,'Auditoria Documental'!$K$7:$K$1000,D$6) -> 0 | E7: =COUNTIFS('Auditoria Documental'!$G$7:$G$1000,$A7,'Auditoria Documental'!$K$7:$K$1000,E$6) -> 0 | F7: =COUNTIFS('Auditoria Documental'!$G$7:$G$1000,$A7,'Auditoria Documental'!$K$7:$K$1000,F$6) -> 7 | G7: =SUM(B7:F7) -> 7 | H7: =IFERROR(SUMIFS('Auditoria Documental'!$N$7:$N$1000,'Auditoria Documental'!$G$7:$G$1000,$A7)/SUMIFS('Auditoria Documental'!$M$7:$M$1000,'Auditoria Documental'!$G$7:$G$1000,$A7),"") -> 0
A8: 2. Secretaria escolar | B8: =COUNTIFS('Auditoria Documental'!$G$7:$G$1000,$A8,'Auditoria Documental'!$K$7:$K$1000,B$6) -> 0 | C8: =COUNTIFS('Auditoria Documental'!$G$7:$G$1000,$A8,'Auditoria Documental'!$K$7:$K$1000,C$6) -> 0 | D8: =COUNTIFS('Auditoria Documental'!$G$7:$G$1000,$A8,'Auditoria Documental'!$K$7:$K$1000,D$6) -> 0 | E8: =COUNTIFS('Auditoria Documental'!$G$7:$G$1000,$A8,'Auditoria Documental'!$K$7:$K$1000,E$6) -> 0 | F8: =COUNTIFS('Auditoria Documental'!$G$7:$G$1000,$A8,'Auditoria Documental'!$K$7:$K$1000,F$6) -> 8 | G8: =SUM(B8:F8) -> 8 | H8: =IFERROR(SUMIFS('Auditoria Documental'!$N$7:$N$1000,'Auditoria Documental'!$G$7:$G$1000,$A8)/SUMIFS('Auditoria Documental'!$M$7:$M$1000,'Auditoria Documental'!$G$7:$G$1000,$A8),"") -> 0
A9: 3. Documentação dos estudantes | B9: =COUNTIFS('Auditoria Documental'!$G$7:$G$1000,$A9,'Auditoria Documental'!$K$7:$K$1000,B$6) -> 0 | C9: =COUNTIFS('Auditoria Documental'!$G$7:$G$1000,$A9,'Auditoria Documental'!$K$7:$K$1000,C$6) -> 0 | D9: =COUNTIFS('Auditoria Documental'!$G$7:$G$1000,$A9,'Auditoria Documental'!$K$7:$K$1000,D$6) -> 0 | E9: =COUNTIFS('Auditoria Documental'!$G$7:$G$1000,$A9,'Auditoria Documental'!$K$7:$K$1000,E$6) -> 0 | F9: =COUNTIFS('Auditoria Documental'!$G$7:$G$1000,$A9,'Auditoria Documental'!$K$7:$K$1000,F$6) -> 9 | G9: =SUM(B9:F9) -> 9 | H9: =IFERROR(SUMIFS('Auditoria Documental'!$N$7:$N$1000,'Auditoria Documental'!$G$7:$G$1000,$A9)/SUMIFS('Auditoria Documental'!$M$7:$M$1000,'Auditoria Documental'!$G$7:$G$1000,$A9),"") -> 0
A10: 4. Documentação dos servidores | B10: =COUNTIFS('Auditoria Documental'!$G$7:$G$1000,$A10,'Auditoria Documental'!$K$7:$K$1000,B$6) -> 0 | C10: =COUNTIFS('Auditoria Documental'!$G$7:$G$1000,$A10,'Auditoria Documental'!$K$7:$K$1000,C$6) -> 0 | D10: =COUNTIFS('Auditoria Documental'!$G$7:$G$1000,$A10,'Auditoria Documental'!$K$7:$K$1000,D$6) -> 0 | E10: =COUNTIFS('Auditoria Documental'!$G$7:$G$1000,$A10,'Auditoria Documental'!$K$7:$K$1000,E$6) -> 0 | F10: =COUNTIFS('Auditoria Documental'!$G$7:$G$1000,$A10,'Auditoria Documental'!$K$7:$K$1000,F$6) -> 5 | G10: =SUM(B10:F10) -> 5 | H10: =IFERROR(SUMIFS('Auditoria Documental'!$N$7:$N$1000,'Auditoria Documental'!$G$7:$G$1000,$A10)/SUMIFS('Auditoria Documental'!$M$7:$M$1000,'Auditoria Documental'!$G$7:$G$1000,$A10),"") -> 0
A11: 5. Documentos administrativos | B11: =COUNTIFS('Auditoria Documental'!$G$7:$G$1000,$A11,'Auditoria Documental'!$K$7:$K$1000,B$6) -> 0 | C11: =COUNTIFS('Auditoria Documental'!$G$7:$G$1000,$A11,'Auditoria Documental'!$K$7:$K$1000,C$6) -> 0 | D11: =COUNTIFS('Auditoria Documental'!$G$7:$G$1000,$A11,'Auditoria Documental'!$K$7:$K$1000,D$6) -> 0 | E11: =COUNTIFS('Auditoria Documental'!$G$7:$G$1000,$A11,'Auditoria Documental'!$K$7:$K$1000,E$6) -> 0 | F11: =COUNTIFS('Auditoria Documental'!$G$7:$G$1000,$A11,'Auditoria Documental'!$K$7:$K$1000,F$6) -> 5 | G11: =SUM(B11:F11) -> 5 | H11: =IFERROR(SUMIFS('Auditoria Documental'!$N$7:$N$1000,'Auditoria Documental'!$G$7:$G$1000,$A11)/SUMIFS('Auditoria Documental'!$M$7:$M$1000,'Auditoria Documental'!$G$7:$G$1000,$A11),"") -> 0
A12: 6. Itens verificados pela CDE | B12: =COUNTIFS('Auditoria Documental'!$G$7:$G$1000,$A12,'Auditoria Documental'!$K$7:$K$1000,B$6) -> 0 | C12: =COUNTIFS('Auditoria Documental'!$G$7:$G$1000,$A12,'Auditoria Documental'!$K$7:$K$1000,C$6) -> 0 | D12: =COUNTIFS('Auditoria Documental'!$G$7:$G$1000,$A12,'Auditoria Documental'!$K$7:$K$1000,D$6) -> 0 | E12: =COUNTIFS('Auditoria Documental'!$G$7:$G$1000,$A12,'Auditoria Documental'!$K$7:$K$1000,E$6) -> 0 | F12: =COUNTIFS('Auditoria Documental'!$G$7:$G$1000,$A12,'Auditoria Documental'!$K$7:$K$1000,F$6) -> 7 | G12: =SUM(B12:F12) -> 7 | H12: =IFERROR(SUMIFS('Auditoria Documental'!$N$7:$N$1000,'Auditoria Documental'!$G$7:$G$1000,$A12)/SUMIFS('Auditoria Documental'!$M$7:$M$1000,'Auditoria Documental'!$G$7:$G$1000,$A12),"") -> 0
A13: 7. Checklist da visita | B13: =COUNTIFS('Auditoria Documental'!$G$7:$G$1000,$A13,'Auditoria Documental'!$K$7:$K$1000,B$6) -> 0 | C13: =COUNTIFS('Auditoria Documental'!$G$7:$G$1000,$A13,'Auditoria Documental'!$K$7:$K$1000,C$6) -> 0 | D13: =COUNTIFS('Auditoria Documental'!$G$7:$G$1000,$A13,'Auditoria Documental'!$K$7:$K$1000,D$6) -> 0 | E13: =COUNTIFS('Auditoria Documental'!$G$7:$G$1000,$A13,'Auditoria Documental'!$K$7:$K$1000,E$6) -> 0 | F13: =COUNTIFS('Auditoria Documental'!$G$7:$G$1000,$A13,'Auditoria Documental'!$K$7:$K$1000,F$6) -> 12 | G13: =SUM(B13:F13) -> 12 | H13: =IFERROR(SUMIFS('Auditoria Documental'!$N$7:$N$1000,'Auditoria Documental'!$G$7:$G$1000,$A13)/SUMIFS('Auditoria Documental'!$M$7:$M$1000,'Auditoria Documental'!$G$7:$G$1000,$A13),"")
A16: DISTRIBUIÇÃO DAS UNIDADES POR DISTRITO | G16: CONSOLIDAÇÃO DAS AUDITORIAS
A17: Distrito | B17: Municipal | C17: OSC/Conveniada | D17: Total | E17: Participação | G17: ID auditoria | H17: Unidade | I17: Situação | J17: Índice | K17: Checklist da visita
A18: DABEL | B18: =COUNTIFS('Cadastro Unidades'!$A$6:$A$222,A18,'Cadastro Unidades'!$C$6:$C$222,"MUNICIPAL") -> 14 | C18: =COUNTIFS('Cadastro Unidades'!$A$6:$A$222,A18,'Cadastro Unidades'!$C$6:$C$222,"OSC/CONVENIADA") -> 3 | D18: =SUM(B18:C18) -> 17 | E18: =IFERROR(D18/COUNTA('Cadastro Unidades'!$E$6:$E$222),0) -> 0.078341014 | G18: =IF('Plano de Auditoria'!$A7="","",'Plano de Auditoria'!A7) -> AUD-002 | H18: =IFERROR(IF('Plano de Auditoria'!$A7="","",'Plano de Auditoria'!B6),"") -> ESCOLA MUNICIPAL PROFESSORA MARIA AUXILIADORA MARTINS GONCALVES | I18: =IF('Plano de Auditoria'!$A7="","",'Plano de Auditoria'!I6) -> Planejada | J18: =IF('Plano de Auditoria'!$A7="","",'Plano de Auditoria'!L6) -> 0 | K18: =IF('Plano de Auditoria'!$A7="","",'Plano de Auditoria'!N6) -> 0
A19: DABEN | B19: =COUNTIFS('Cadastro Unidades'!$A$6:$A$222,A19,'Cadastro Unidades'!$C$6:$C$222,"MUNICIPAL") -> 35 | C19: =COUNTIFS('Cadastro Unidades'!$A$6:$A$222,A19,'Cadastro Unidades'!$C$6:$C$222,"OSC/CONVENIADA") -> 10 | D19: =SUM(B19:C19) -> 45 | E19: =IFERROR(D19/COUNTA('Cadastro Unidades'!$E$6:$E$222),0) -> 0.20737327 | G19: =IF(#REF!="","",#REF!) -> #REF! | H19: =IFERROR(IF(#REF!="","",'Plano de Auditoria'!B7),"") | I19: =IF(#REF!="","",'Plano de Auditoria'!I7) -> #REF! | J19: =IF(#REF!="","",'Plano de Auditoria'!L7) -> #REF! | K19: =IF(#REF!="","",'Plano de Auditoria'!N7) -> #REF!
A20: DAENT | B20: =COUNTIFS('Cadastro Unidades'!$A$6:$A$222,A20,'Cadastro Unidades'!$C$6:$C$222,"MUNICIPAL") -> 19 | C20: =COUNTIFS('Cadastro Unidades'!$A$6:$A$222,A20,'Cadastro Unidades'!$C$6:$C$222,"OSC/CONVENIADA") -> 3 | D20: =SUM(B20:C20) -> 22 | E20: =IFERROR(D20/COUNTA('Cadastro Unidades'!$E$6:$E$222),0) -> 0.10138249 | G20: =IF('Plano de Auditoria'!$A8="","",'Plano de Auditoria'!A8) -> AUD-003 | H20: =IFERROR(IF('Plano de Auditoria'!$A8="","",'Plano de Auditoria'!B8),"") -> ESCOLA MUNICIPAL PROF MIGUEL PERNAMBUCO FILHO | I20: =IF('Plano de Auditoria'!$A8="","",'Plano de Auditoria'!I8) | J20: =IF('Plano de Auditoria'!$A8="","",'Plano de Auditoria'!L8) -> 0 | K20: =IF('Plano de Auditoria'!$A8="","",'Plano de Auditoria'!N8) -> 0
A21: DAGUA | B21: =COUNTIFS('Cadastro Unidades'!$A$6:$A$222,A21,'Cadastro Unidades'!$C$6:$C$222,"MUNICIPAL") -> 31 | C21: =COUNTIFS('Cadastro Unidades'!$A$6:$A$222,A21,'Cadastro Unidades'!$C$6:$C$222,"OSC/CONVENIADA") -> 8 | D21: =SUM(B21:C21) -> 39 | E21: =IFERROR(D21/COUNTA('Cadastro Unidades'!$E$6:$E$222),0) -> 0.1797235 | G21: =IF('Plano de Auditoria'!$A9="","",'Plano de Auditoria'!A9) -> AUD-004 | H21: =IFERROR(IF('Plano de Auditoria'!$A9="","",'Plano de Auditoria'!B9),"") -> ANEXO CASA DA CRIANCA SANTA INES DA EM ALZIRA PERNAMBUCO | I21: =IF('Plano de Auditoria'!$A9="","",'Plano de Auditoria'!I9) | J21: =IF('Plano de Auditoria'!$A9="","",'Plano de Auditoria'!L9) -> 0 | K21: =IF('Plano de Auditoria'!$A9="","",'Plano de Auditoria'!N9) -> 0
A22: DAICO | B22: =COUNTIFS('Cadastro Unidades'!$A$6:$A$222,A22,'Cadastro Unidades'!$C$6:$C$222,"MUNICIPAL") -> 24 | C22: =COUNTIFS('Cadastro Unidades'!$A$6:$A$222,A22,'Cadastro Unidades'!$C$6:$C$222,"OSC/CONVENIADA") -> 9 | D22: =SUM(B22:C22) -> 33 | E22: =IFERROR(D22/COUNTA('Cadastro Unidades'!$E$6:$E$222),0) -> 0.15207373 | G22: =IF('Plano de Auditoria'!$A10="","",'Plano de Auditoria'!A10) -> AUD-005 | H22: =IFERROR(IF('Plano de Auditoria'!$A10="","",'Plano de Auditoria'!B10),"") -> CENTRO EDUCACIONAL ARTE DE EDUCAR OSC ANEXO INSTITUTO ACELERA AMAZONIA | I22: =IF('Plano de Auditoria'!$A10="","",'Plano de Auditoria'!I10) | J22: =IF('Plano de Auditoria'!$A10="","",'Plano de Auditoria'!L10) -> 0 | K22: =IF('Plano de Auditoria'!$A10="","",'Plano de Auditoria'!N10) -> 0
A23: DAMOS | B23: =COUNTIFS('Cadastro Unidades'!$A$6:$A$222,A23,'Cadastro Unidades'!$C$6:$C$222,"MUNICIPAL") -> 15 | C23: =COUNTIFS('Cadastro Unidades'!$A$6:$A$222,A23,'Cadastro Unidades'!$C$6:$C$222,"OSC/CONVENIADA") -> 4 | D23: =SUM(B23:C23) -> 19 | E23: =IFERROR(D23/COUNTA('Cadastro Unidades'!$E$6:$E$222),0) -> 0.087557604 | G23: =IF('Plano de Auditoria'!$A11="","",'Plano de Auditoria'!A11) -> AUD-006 | H23: =IFERROR(IF('Plano de Auditoria'!$A11="","",'Plano de Auditoria'!B11),"") -> ESCOLA MUNICIPAL ALZIRA PERNAMBUCO | I23: =IF('Plano de Auditoria'!$A11="","",'Plano de Auditoria'!I11) | J23: =IF('Plano de Auditoria'!$A11="","",'Plano de Auditoria'!L11) -> 0 | K23: =IF('Plano de Auditoria'!$A11="","",'Plano de Auditoria'!N11) -> 0
A24: DAOUT | B24: =COUNTIFS('Cadastro Unidades'!$A$6:$A$222,A24,'Cadastro Unidades'!$C$6:$C$222,"MUNICIPAL") -> 18 | C24: =COUNTIFS('Cadastro Unidades'!$A$6:$A$222,A24,'Cadastro Unidades'!$C$6:$C$222,"OSC/CONVENIADA") -> 2 | D24: =SUM(B24:C24) -> 20 | E24: =IFERROR(D24/COUNTA('Cadastro Unidades'!$E$6:$E$222),0) -> 0.092165899 | G24: =IF('Plano de Auditoria'!$A12="","",'Plano de Auditoria'!A12) -> AUD-007 | H24: =IFERROR(IF('Plano de Auditoria'!$A12="","",'Plano de Auditoria'!B12),"") -> ESCOLA MUNICIPAL LIONS CLUBE DE BELEM | I24: =IF('Plano de Auditoria'!$A12="","",'Plano de Auditoria'!I12) | J24: =IF('Plano de Auditoria'!$A12="","",'Plano de Auditoria'!L12) -> 0 | K24: =IF('Plano de Auditoria'!$A12="","",'Plano de Auditoria'!N12) -> 0
A25: DASAC | B25: =COUNTIFS('Cadastro Unidades'!$A$6:$A$222,A25,'Cadastro Unidades'!$C$6:$C$222,"MUNICIPAL") -> 19 | C25: =COUNTIFS('Cadastro Unidades'!$A$6:$A$222,A25,'Cadastro Unidades'!$C$6:$C$222,"OSC/CONVENIADA") -> 3 | D25: =SUM(B25:C25) -> 22 | E25: =IFERROR(D25/COUNTA('Cadastro Unidades'!$E$6:$E$222),0) -> 0.10138249 | G25: =IF('Plano de Auditoria'!$A13="","",'Plano de Auditoria'!A13) -> AUD-008 | H25: =IFERROR(IF('Plano de Auditoria'!$A13="","",'Plano de Auditoria'!B13),"") -> ESCOLA MUNICIPAL PROFESSORA LUCIA SOARES CASTRO | I25: =IF('Plano de Auditoria'!$A13="","",'Plano de Auditoria'!I13) | J25: =IF('Plano de Auditoria'!$A13="","",'Plano de Auditoria'!L13) -> 0 | K25: =IF('Plano de Auditoria'!$A13="","",'Plano de Auditoria'!N13) -> 0
G26: =IF('Plano de Auditoria'!$A14="","",'Plano de Auditoria'!A14) -> AUD-009 | H26: =IFERROR(IF('Plano de Auditoria'!$A14="","",'Plano de Auditoria'!B14),"") -> ESCOLA MUNICIPAL PROFESSORA RAIMUNDA LUCIA GUERREIRO | I26: =IF('Plano de Auditoria'!$A14="","",'Plano de Auditoria'!I14) | J26: =IF('Plano de Auditoria'!$A14="","",'Plano de Auditoria'!L14) -> 0 | K26: =IF('Plano de Auditoria'!$A14="","",'Plano de Auditoria'!N14) -> 0
G27: =IF('Plano de Auditoria'!$A15="","",'Plano de Auditoria'!A15) -> AUD-010 | H27: =IFERROR(IF('Plano de Auditoria'!$A15="","",'Plano de Auditoria'!B15),"") -> ESCOLA MUNICIPAL RUY DA SILVEIRA BRITTO | I27: =IF('Plano de Auditoria'!$A15="","",'Plano de Auditoria'!I15) | J27: =IF('Plano de Auditoria'!$A15="","",'Plano de Auditoria'!L15) -> 0 | K27: =IF('Plano de Auditoria'!$A15="","",'Plano de Auditoria'!N15) -> 0
G28: =IF('Plano de Auditoria'!$A16="","",'Plano de Auditoria'!A16) -> AUD-011 | H28: =IFERROR(IF('Plano de Auditoria'!$A16="","",'Plano de Auditoria'!B16),"") -> CENTRO DE REFERENCIA DE EDUCACAO INFANTIL PROF ORLANDO BITAR | I28: =IF('Plano de Auditoria'!$A16="","",'Plano de Auditoria'!I16) | J28: =IF('Plano de Auditoria'!$A16="","",'Plano de Auditoria'!L16) -> 0 | K28: =IF('Plano de Auditoria'!$A16="","",'Plano de Auditoria'!N16) -> 0
G29: =IF('Plano de Auditoria'!$A17="","",'Plano de Auditoria'!A17) -> AUD-012 | H29: =IFERROR(IF('Plano de Auditoria'!$A17="","",'Plano de Auditoria'!B17),"") -> INSTITUTO FELIPE SMALDONE BELEM | I29: =IF('Plano de Auditoria'!$A17="","",'Plano de Auditoria'!I17) | J29: =IF('Plano de Auditoria'!$A17="","",'Plano de Auditoria'!L17) -> 0 | K29: =IF('Plano de Auditoria'!$A17="","",'Plano de Auditoria'!N17) -> 0
G30: =IF('Plano de Auditoria'!$A18="","",'Plano de Auditoria'!A18) -> AUD-013 | H30: =IFERROR(IF('Plano de Auditoria'!$A18="","",'Plano de Auditoria'!B18),"") -> CRECHE CASA LAR CORDEIRINHO DE DEUS | I30: =IF('Plano de Auditoria'!$A18="","",'Plano de Auditoria'!I18) | J30: =IF('Plano de Auditoria'!$A18="","",'Plano de Auditoria'!L18) -> 0 | K30: =IF('Plano de Auditoria'!$A18="","",'Plano de Auditoria'!N18) -> 0
G31: =IF('Plano de Auditoria'!$A19="","",'Plano de Auditoria'!A19) -> AUD-014 | H31: =IFERROR(IF('Plano de Auditoria'!$A19="","",'Plano de Auditoria'!B19),"") -> ESCOLA MUNICIPAL BENVINDA DE FRANCA MESSIAS | I31: =IF('Plano de Auditoria'!$A19="","",'Plano de Auditoria'!I19) | J31: =IF('Plano de Auditoria'!$A19="","",'Plano de Auditoria'!L19) -> 0 | K31: =IF('Plano de Auditoria'!$A19="","",'Plano de Auditoria'!N19) -> 0
G32: =IF('Plano de Auditoria'!$A20="","",'Plano de Auditoria'!A20) -> AUD-015 | H32: =IFERROR(IF('Plano de Auditoria'!$A20="","",'Plano de Auditoria'!B20),"") -> ESCOLA MUNICIPAL ERNESTINA RODRIGUES | I32: =IF('Plano de Auditoria'!$A20="","",'Plano de Auditoria'!I20) | J32: =IF('Plano de Auditoria'!$A20="","",'Plano de Auditoria'!L20) -> 0 | K32: =IF('Plano de Auditoria'!$A20="","",'Plano de Auditoria'!N20) -> 0
G33: =IF('Plano de Auditoria'!$A21="","",'Plano de Auditoria'!A21) -> AUD-016 | H33: =IFERROR(IF('Plano de Auditoria'!$A21="","",'Plano de Auditoria'!B21),"") -> ESCOLA MUNICIPAL FRANCISCO DA SILVA NUNES | I33: =IF('Plano de Auditoria'!$A21="","",'Plano de Auditoria'!I21) | J33: =IF('Plano de Auditoria'!$A21="","",'Plano de Auditoria'!L21) -> 0 | K33: =IF('Plano de Auditoria'!$A21="","",'Plano de Auditoria'!N21) -> 0
G34: =IF('Plano de Auditoria'!$A22="","",'Plano de Auditoria'!A22) -> AUD-017 | H34: =IFERROR(IF('Plano de Auditoria'!$A22="","",'Plano de Auditoria'!B22),"") -> ANEXO SOLAR ACALANTO DA EM BENVINDA DE FRANCA MESSIAS | I34: =IF('Plano de Auditoria'!$A22="","",'Plano de Auditoria'!I22) | J34: =IF('Plano de Auditoria'!$A22="","",'Plano de Auditoria'!L22) -> 0 | K34: =IF('Plano de Auditoria'!$A22="","",'Plano de Auditoria'!N22) -> 0
G35: =IF('Plano de Auditoria'!$A23="","",'Plano de Auditoria'!A23) -> AUD-018 | H35: =IFERROR(IF('Plano de Auditoria'!$A23="","",'Plano de Auditoria'!B23),"") -> CENTRO COMUNITARIO NOSSA SENHORA DO PERPETUO SOCORRO | I35: =IF('Plano de Auditoria'!$A23="","",'Plano de Auditoria'!I23) | J35: =IF('Plano de Auditoria'!$A23="","",'Plano de Auditoria'!L23) -> 0 | K35: =IF('Plano de Auditoria'!$A23="","",'Plano de Auditoria'!N23) -> 0
G36: =IF('Plano de Auditoria'!$A24="","",'Plano de Auditoria'!A24) -> AUD-019 | H36: =IFERROR(IF('Plano de Auditoria'!$A24="","",'Plano de Auditoria'!B24),"") -> ESCOLA MUNICIPAL AUGUSTO MEIRA FILHO | I36: =IF('Plano de Auditoria'!$A24="","",'Plano de Auditoria'!I24) | J36: =IF('Plano de Auditoria'!$A24="","",'Plano de Auditoria'!L24) -> 0 | K36: =IF('Plano de Auditoria'!$A24="","",'Plano de Auditoria'!N24) -> 0
G37: =IF('Plano de Auditoria'!$A25="","",'Plano de Auditoria'!A25) -> AUD-020 | H37: =IFERROR(IF('Plano de Auditoria'!$A25="","",'Plano de Auditoria'!B25),"") -> ESCOLA MUNICIPAL MARIA AMORAS DE OLIVEIRA | I37: =IF('Plano de Auditoria'!$A25="","",'Plano de Auditoria'!I25) | J37: =IF('Plano de Auditoria'!$A25="","",'Plano de Auditoria'!L25) -> 0 | K37: =IF('Plano de Auditoria'!$A25="","",'Plano de Auditoria'!N25) -> 0
... G47: =IF('Plano de Auditoria'!$A35="","",'Plano de Auditoria'!A35) -> AUD-030 | H47: =IFERROR(IF('Plano de Auditoria'!$A35="","",'Plano de Auditoria'!B35),"") -> ESCOLA MUNICIPAL PADRE BRUNO SECHI | I47: =IF('Plano de Auditoria'!$A35="","",'Plano de Auditoria'!I35) | J47: =IF('Plano de Auditoria'!$A35="","",'Plano de Auditoria'!L35) -> 0 | K47: =IF('Plano de Auditoria'!$A35="","",'Plano de Auditoria'!N35) -> 0
